Workbook

Sheet MonthlyMetric
A1: Tutor Name | B1: Date Range | C1: % to Delivery Target | D1: % to Availability Target | E1: % Sessions on Time | F1: % Parents Updates Done on Time | G1: % of Active Students with Progress Updates Completed in last 2 months | H1: Weighted Repurchases | I1: OLD PPW | J1: Ratio of PPW Events with Attached PPWs | K1: Tier | L1: Adjunct/Professional | M1: Faculty Leader
A2: Aaron Schneberger | B2: 10/5/25 - 11/1/25 | C2: 1.2813 | D2: 1.1602 | E2: 1 | F2: 1 | G2: 0.90909091 | H2: 3 | I2: 2/4 | J2: 0.5 | K2: =VLOOKUP(A2,MasterTutor!A:D,4,FALSE) -> #N/A | L2: =VLOOKUP(A2,MasterTutor!A:D,3,FALSE) -> #N/A | M2: =VLOOKUP(A2,MasterTutor!A:D,2,FALSE) -> #N/A
A3: Aaron Schneberger | B3: 11/2/25 - 11/29/25 | C3: 0.76 | D3: 0.78 | E3: 1 | F3: 1 | G3: 0.91 | H3: 1 | K3: =VLOOKUP(A3,MasterTutor!A:D,4,FALSE) -> #N/A | L3: =VLOOKUP(A3,MasterTutor!A:D,3,FALSE) -> #N/A | M3: =VLOOKUP(A3,MasterTutor!A:D,2,FALSE) -> #N/A
A4: Aaron Schneberger | B4: 5/18/25 - 6/14/25 | C4: 0.74 | D4: 0.9 | E4: 0.99 | F4: 1 | G4: 1 | H4: 10 | I4: 1 | J4: =I4 -> 1 | K4: =VLOOKUP(A4,MasterTutor!A:D,4,FALSE) -> #N/A | L4: =VLOOKUP(A4,MasterTutor!A:D,3,FALSE) -> #N/A | M4: =VLOOKUP(A4,MasterTutor!A:D,2,FALSE) -> #N/A
A5: Aaron Schneberger | B5: 6/15/25 - 7/12/25 | C5: 0.5 | D5: 0.81 | E5: 1 | F5: 0.93 | G5: 0.7 | H5: 2 | I5: 2/3 | J5: 0.67 | K5: =VLOOKUP(A5,MasterTutor!A:D,4,FALSE) -> #N/A | L5: =VLOOKUP(A5,MasterTutor!A:D,3,FALSE) -> #N/A | M5: =VLOOKUP(A5,MasterTutor!A:D,2,FALSE) -> #N/A
A6: Aaron Schneberger | B6: 7/13/25 - 8/10/25 | C6: 0.48 | D6: 0.5 | E6: 1 | F6: 1 | G6: 0.71 | H6: 3 | I6: 1 | J6: =I6 -> 1 | K6: =VLOOKUP(A6,MasterTutor!A:D,4,FALSE) -> #N/A | L6: =VLOOKUP(A6,MasterTutor!A:D,3,FALSE) -> #N/A | M6: =VLOOKUP(A6,MasterTutor!A:D,2,FALSE) -> #N/A
A7: Aaron Schneberger | B7: 8/10/25 - 9/6/25 | C7: 1.2 | D7: 1.24 | E7: 1 | F7: 1 | G7: 1 | H7: 4 | K7: =VLOOKUP(A7,MasterTutor!A:D,4,FALSE) -> #N/A | L7: =VLOOKUP(A7,MasterTutor!A:D,3,FALSE) -> #N/A | M7: =VLOOKUP(A7,MasterTutor!A:D,2,FALSE) -> #N/A
A8: Aaron Schneberger | B8: 9/7/25 - 10/4/25 | C8: 1.06 | D8: 1.1 | E8: 1 | F8: 0.97 | G8: 0.82 | H8: 6 | I8: 1/1 | J8: 1 | K8: =VLOOKUP(A8,MasterTutor!A:D,4,FALSE) -> #N/A | L8: =VLOOKUP(A8,MasterTutor!A:D,3,FALSE) -> #N/A | M8: =VLOOKUP(A8,MasterTutor!A:D,2,FALSE) -> #N/A
A9: Akeema Williams | B9: 10/5/25 - 11/1/25 | C9: 1.0917 | D9: 1.1118 | E9: 0.99259259 | F9: 0.97916667 | G9: 0.96153846 | H9: 14 | I9: 6/10 | J9: 0.6 | K9: =VLOOKUP(A9,MasterTutor!A:D,4,FALSE) -> Advanced | L9: =VLOOKUP(A9,MasterTutor!A:D,3,FALSE) -> Professional | M9: =VLOOKUP(A9,MasterTutor!A:D,2,FALSE) -> Ian Plamondon
A10: Akeema Williams | B10: 11/2/25 - 11/29/25 | C10: 0.93 | D10: 0.96 | E10: 0.99 | F10: 0.97 | G10: 0.76 | H10: 11 | I10: 45664 | J10: 0.0014285714 | K10: =VLOOKUP(A10,MasterTutor!A:D,4,FALSE) -> Advanced | L10: =VLOOKUP(A10,MasterTutor!A:D,3,FALSE) -> Professional | M10: =VLOOKUP(A10,MasterTutor!A:D,2,FALSE) -> Ian Plamondon
A11: Akeema Williams | B11: 5/18/25 - 6/14/25 | C11: 0.75 | D11: 1.01 | E11: 1 | F11: 1 | G11: 0.9 | H11: 2 | I11: 1/2 | J11: 0.5 | K11: =VLOOKUP(A11,MasterTutor!A:D,4,FALSE) -> Advanced | L11: =VLOOKUP(A11,MasterTutor!A:D,3,FALSE) -> Professional | M11: =VLOOKUP(A11,MasterTutor!A:D,2,FALSE) -> Ian Plamondon
A12: Akeema Williams | B12: 6/15/25 - 7/12/25 | C12: 0.62 | D12: 0.92 | E12: 1 | F12: 0.77 | G12: 0.64 | H12: 2 | I12: 0 | J12: =I12 -> 0 | K12: =VLOOKUP(A12,MasterTutor!A:D,4,FALSE) -> Advanced | L12: =VLOOKUP(A12,MasterTutor!A:D,3,FALSE) -> Professional | M12: =VLOOKUP(A12,MasterTutor!A:D,2,FALSE) -> Ian Plamondon
A13: Akeema Williams | B13: 7/13/25 - 8/10/25 | C13: 0.94 | D13: 0.98 | E13: 0.99 | F13: 1 | G13: 0.46 | H13: 6 | I13: 2/3 | J13: 0.67 | K13: =VLOOKUP(A13,MasterTutor!A:D,4,FALSE) -> Advanced | L13: =VLOOKUP(A13,MasterTutor!A:D,3,FALSE) -> Professional | M13: =VLOOKUP(A13,MasterTutor!A:D,2,FALSE) -> Ian Plamondon
A14: Akeema Williams | B14: 8/10/25 - 9/6/25 | C14: 0.8 | D14: 0.97 | E14: 1 | F14: 0.99 | G14: 0.91 | H14: 10 | I14: 1/3 | J14: 0.33 | K14: =VLOOKUP(A14,MasterTutor!A:D,4,FALSE) -> Advanced | L14: =VLOOKUP(A14,MasterTutor!A:D,3,FALSE) -> Professional | M14: =VLOOKUP(A14,MasterTutor!A:D,2,FALSE) -> Ian Plamondon
A15: Akeema Williams | B15: 9/7/25 - 10/4/25 | C15: 0.96 | D15: 1.01 | E15: 0.99 | F15: 0.97 | G15: 0.74 | H15: 13 | I15: 4/6 | J15: 0.67 | K15: =VLOOKUP(A15,MasterTutor!A:D,4,FALSE) -> Advanced | L15: =VLOOKUP(A15,MasterTutor!A:D,3,FALSE) -> Professional | M15: =VLOOKUP(A15,MasterTutor!A:D,2,FALSE) -> Ian Plamondon
A16: Akeema Williams | B16: 11/30/25 - 12/27/25 | C16: 0.98 | D16: 0.98 | E16: 1 | F16: 0.95 | G16: 0.9 | H16: 19 | K16: =VLOOKUP(A16,MasterTutor!A:D,4,FALSE) -> Advanced | L16: =VLOOKUP(A16,MasterTutor!A:D,3,FALSE) -> Professional | M16: =VLOOKUP(A16,MasterTutor!A:D,2,FALSE) -> Ian Plamondon
A17: Alex Small | B17: 10/5/25 - 11/1/25 | C17: 0.9688 | D17: 1.5156 | E17: 1 | F17: 1 | G17: 0.5 | H17: 3 | I17: 1/1 | J17: 1 | K17: =VLOOKUP(A17,MasterTutor!A:D,4,FALSE) -> Premium | L17: =VLOOKUP(A17,MasterTutor!A:D,3,FALSE) -> Adjunct | M17: =VLOOKUP(A17,MasterTutor!A:D,2,FALSE) -> Ela Cross
A18: Alex Small | B18: 11/2/25 - 11/29/25 | C18: 0.8 | D18: 1.54 | E18: 1 | F18: 0.9 | G18: 0.88 | H18: 2 | K18: =VLOOKUP(A18,MasterTutor!A:D,4,FALSE) -> Premium | L18: =VLOOKUP(A18,MasterTutor!A:D,3,FALSE) -> Adjunct | M18: =VLOOKUP(A18,MasterTutor!A:D,2,FALSE) -> Ela Cross
A19: Alex Small | B19: 5/18/25 - 6/14/25 | C19: 0.31 | D19: 1 | E19: 1 | F19: 0.6 | G19: #N/A | H19: 1 | K19: =VLOOKUP(A19,MasterTutor!A:D,4,FALSE) -> Premium | L19: =VLOOKUP(A19,MasterTutor!A:D,3,FALSE) -> Adjunct | M19: =VLOOKUP(A19,MasterTutor!A:D,2,FALSE) -> Ela Cross
A20: Alex Small | B20: 6/15/25 - 7/12/25 | C20: 0 | D20: 0.79 | E20: 0 | F20: 0 | G20: 0 | H20: #N/A | K20: =VLOOKUP(A20,MasterTutor!A:D,4,FALSE) -> Premium | L20: =VLOOKUP(A20,MasterTutor!A:D,3,FALSE) -> Adjunct | M20: =VLOOKUP(A20,MasterTutor!A:D,2,FALSE) -> Ela Cross
A21: Alex Small | B21: 7/13/25 - 8/10/25 | C21: 0 | D21: 1 | E21: 0 | F21: 0 | G21: 0 | H21: #N/A | K21: =VLOOKUP(A21,MasterTutor!A:D,4,FALSE) -> Premium | L21: =VLOOKUP(A21,MasterTutor!A:D,3,FALSE) -> Adjunct | M21: =VLOOKUP(A21,MasterTutor!A:D,2,FALSE) -> Ela Cross
A22: Alex Small | B22: 8/10/25 - 9/6/25 | C22: 0.76 | D22: 1.42 | E22: 1 | F22: 1 | G22: 0 | H22: 2 | I22: 3/5 | J22: 0.6 | K22: =VLOOKUP(A22,MasterTutor!A:D,4,FALSE) -> Premium | L22: =VLOOKUP(A22,MasterTutor!A:D,3,FALSE) -> Adjunct | M22: =VLOOKUP(A22,MasterTutor!A:D,2,FALSE) -> Ela Cross
A23: Alex Small | B23: 9/7/25 - 10/4/25 | C23: 1.14 | D23: 1.46 | E23: 1 | F23: 0.73 | G23: 0 | H23: 3 | K23: =VLOOKUP(A23,MasterTutor!A:D,4,FALSE) -> Premium | L23: =VLOOKUP(A23,MasterTutor!A:D,3,FALSE) -> Adjunct | M23: =VLOOKUP(A23,MasterTutor!A:D,2,FALSE) -> Ela Cross
A24: Alex Small | B24: 11/30/25 - 12/27/25 | C24: 0.35 | D24: 1.4 | E24: 1 | F24: 0.91 | G24: 0.67 | H24: 0 | K24: =VLOOKUP(A24,MasterTutor!A:D,4,FALSE) -> Premium | L24: =VLOOKUP(A24,MasterTutor!A:D,3,FALSE) -> Adjunct | M24: =VLOOKUP(A24,MasterTutor!A:D,2,FALSE) -> Ela Cross
A25: Alexa Pinera | B25: 10/5/25 - 11/1/25 | C25: 0.6257 | D25: 2.2516 | E25: 0.94029851 | F25: 0.97619048 | G25: 0.75 | H25: 1 | I25: 4/4 | J25: 1 | K25: =VLOOKUP(A25,MasterTutor!A:D,4,FALSE) -> Premium | L25: =VLOOKUP(A25,MasterTutor!A:D,3,FALSE) -> Professional | M25: =VLOOKUP(A25,MasterTutor!A:D,2,FALSE) -> Ian Plamondon
A26: Alexa Pinera | B26: 11/2/25 - 11/29/25 | C26: 0.7 | D26: 1.99 | E26: 0.97 | F26: 1 | G26: 0.71 | H26: 5 | I26: 45691 | J26: 0.0066666667 | K26: =VLOOKUP(A26,MasterTutor!A:D,4,FALSE) -> Premium | L26: =VLOOKUP(A26,MasterTutor!A:D,3,FALSE) -> Professional | M26: =VLOOKUP(A26,MasterTutor!A:D,2,FALSE) -> Ian Plamondon
A27: Alexa Pinera | B27: 5/18/25 - 6/14/25 | C27: 0.96 | D27: 1.65 | E27: 0.97 | F27: 1 | G27: 0.9 | H27: 0 | I27: 3/4 | J27: 0.75 | K27: =VLOOKUP(A27,MasterTutor!A:D,4,FALSE) -> Premium | L27: =VLOOKUP(A27,MasterTutor!A:D,3,FALSE) -> Professional | M27: =VLOOKUP(A27,MasterTutor!A:D,2,FALSE) -> Ian Plamondon
A28: Alexa Pinera | B28: 6/15/25 - 7/12/25 | C28: 0.52 | D28: 1.83 | E28: 0.99 | F28: 1 | G28: 0.77 | H28: 2 | I28: 1 | J28: =I28 -> 1 | K28: =VLOOKUP(A28,MasterTutor!A:D,4,FALSE) -> Premium | L28: =VLOOKUP(A28,MasterTutor!A:D,3,FALSE) -> Professional | M28: =VLOOKUP(A28,MasterTutor!A:D,2,FALSE) -> Ian Plamondon
A29: Alexa Pinera | B29: 7/13/25 - 8/10/25 | C29: 0.82 | D29: 1.92 | E29: 0.96 | F29: 1 | G29: 0.56 | H29: 2 | I29: 1 | J29: =I29 -> 1 | K29: =VLOOKUP(A29,MasterTutor!A:D,4,FALSE) -> Premium | L29: =VLOOKUP(A29,MasterTutor!A:D,3,FALSE) -> Professional | M29: =VLOOKUP(A29,MasterTutor!A:D,2,FALSE) -> Ian Plamondon
A30: Alexa Pinera | B30: 8/10/25 - 9/6/25 | C30: 0.8 | D30: 1.03 | E30: 0.99 | F30: 1 | G30: 0.88 | H30: 1 | I30: 0/1 | J30: 0 | K30: =VLOOKUP(A30,MasterTutor!A:D,4,FALSE) -> Premium | L30: =VLOOKUP(A30,MasterTutor!A:D,3,FALSE) -> Professional | M30: =VLOOKUP(A30,MasterTutor!A:D,2,FALSE) -> Ian Plamondon
A31: Alexa Pinera | B31: 9/7/25 - 10/4/25 | C31: 0.75 | D31: 2.19 | E31: 0.94 | F31: 1 | G31: 0.93 | H31: 0 | I31: 3/3 | J31: 1 | K31: =VLOOKUP(A31,MasterTutor!A:D,4,FALSE) -> Premium | L31: =VLOOKUP(A31,MasterTutor!A:D,3,FALSE) -> Professional | M31: =VLOOKUP(A31,MasterTutor!A:D,2,FALSE) -> Ian Plamondon
A32: Alexa Pinera | B32: 11/30/25 - 12/27/25 | C32: 0.6 | D32: 1.82 | E32: 1 | F32: 0.98 | G32: 0.81 | H32: 4 | I32: 1 | J32: 1 | K32: =VLOOKUP(A32,MasterTutor!A:D,4,FALSE) -> Premium | L32: =VLOOKUP(A32,MasterTutor!A:D,3,FALSE) -> Professional | M32: =VLOOKUP(A32,MasterTutor!A:D,2,FALSE) -> Ian Plamondon
A33: Alexandra Berrios | B33: 10/5/25 - 11/1/25 | C33: 1.7344 | D33: 1.3555 | E33: 0.98888889 | F33: 0.78125 | G33: 0.70588235 | H33: 7 | I33: 2/3 | J33: 0.66 | K33: =VLOOKUP(A33,MasterTutor!A:D,4,FALSE) -> Advanced | L33: =VLOOKUP(A33,MasterTutor!A:D,3,FALSE) -> Adjunct | M33: =VLOOKUP(A33,MasterTutor!A:D,2,FALSE) -> Kristin Haase-Alvey
A34: Alexandra Berrios | B34: 10/5/25 - 11/1/25 | C34: 1.7344 | D34: 1.3555 | E34: 0.98888889 | F34: 0.78125 | G34: 0.70588235 | H34: 7 | I34: 2/3 | J34: =_xlfn.TEXTBEFORE(I34, "/")/_xlfn.TEXTAFTER(I34,"/") -> 0.66666667 | K34: =VLOOKUP(A34,MasterTutor!A:D,4,FALSE) -> Advanced | L34: =VLOOKUP(A34,MasterTutor!A:D,3,FALSE) -> Adjunct | M34: =VLOOKUP(A34,MasterTutor!A:D,2,FALSE) -> Kristin Haase-Alvey
A35: Alexandra Berrios | B35: 11/2/25 - 11/29/25 | C35: 1.67 | D35: 1.38 | E35: 1 | F35: 0.47 | G35: 0.81 | H35: 11 | I35: 0/5 | J35: 0 | K35: =VLOOKUP(A35,MasterTutor!A:D,4,FALSE) -> Advanced | L35: =VLOOKUP(A35,MasterTutor!A:D,3,FALSE) -> Adjunct | M35: =VLOOKUP(A35,MasterTutor!A:D,2,FALSE) -> Kristin Haase-Alvey
A36: Alexandra Berrios | B36: 5/18/25 - 6/14/25 | C36: 0.54 | D36: 0.97 | E36: 1 | F36: 0.85 | G36: 1 | H36: 1 | K36: =VLOOKUP(A36,MasterTutor!A:D,4,FALSE) -> Advanced | L36: =VLOOKUP(A36,MasterTutor!A:D,3,FALSE) -> Adjunct | M36: =VLOOKUP(A36,MasterTutor!A:D,2,FALSE) -> Kristin Haase-Alvey
A37: Alexandra Berrios | B37: 6/15/25 - 7/12/25 | C37: 0.02 | D37: 0.63 | E37: 1 | F37: 1 | G37: 1 | H37: #N/A | K37: =VLOOKUP(A37,MasterTutor!A:D,4,FALSE) -> Advanced | L37: =VLOOKUP(A37,MasterTutor!A:D,3,FALSE) -> Adjunct | M37: =VLOOKUP(A37,MasterTutor!A:D,2,FALSE) -> Kristin Haase-Alvey
A38: Alexandra Berrios | B38: 7/13/25 - 8/10/25 | C38: 0.8 | D38: 1.29 | E38: 1 | F38: 0.87 | G38: 0.8 | H38: #N/A | I38: 1 | J38: =I38 -> 1 | K38: =VLOOKUP(A38,MasterTutor!A:D,4,FALSE) -> Advanced | L38: =VLOOKUP(A38,MasterTutor!A:D,3,FALSE) -> Adjunct | M38: =VLOOKUP(A38,MasterTutor!A:D,2,FALSE) -> Kristin Haase-Alvey
A39: Alexandra Berrios | B39: 8/10/25 - 9/6/25 | C39: 1.02 | D39: 1.48 | E39: 1 | F39: 0.95 | G39: 0.4 | H39: 2 | K39: =VLOOKUP(A39,MasterTutor!A:D,4,FALSE) -> Advanced | L39: =VLOOKUP(A39,MasterTutor!A:D,3,FALSE) -> Adjunct | M39: =VLOOKUP(A39,MasterTutor!A:D,2,FALSE) -> Kristin Haase-Alvey
A40: Alexandra Berrios | B40: 9/7/25 - 10/4/25 | C40: 1.85 | D40: 1.65 | E40: 1 | F40: 0.75 | G40: 0.58 | H40: 8 | I40: 5/6 | J40: 0.83 | K40: =VLOOKUP(A40,MasterTutor!A:D,4,FALSE) -> Advanced | L40: =VLOOKUP(A40,MasterTutor!A:D,3,FALSE) -> Adjunct | M40: =VLOOKUP(A40,MasterTutor!A:D,2,FALSE) -> Kristin Haase-Alvey
A41: Alexandra Berrios | B41: 11/30/25 - 12/27/25 | C41: 1.09 | D41: 0.93 | E41: 0.95 | F41: 0.51 | G41: 0.65 | H41: 3 | I41: 1 | J41: 1 | K41: =VLOOKUP(A41,MasterTutor!A:D,4,FALSE) -> Advanced | L41: =VLOOKUP(A41,MasterTutor!A:D,3,FALSE) -> Adjunct | M41: =VLOOKUP(A41,MasterTutor!A:D,2,FALSE) -> Kristin Haase-Alvey
A42: Alexis Boucher | B42: 10/5/25 - 11/1/25 | C42: 0.7208 | D42: 0.9868 | E42: 1 | F42: 0.87272727 | G42: 0.95652174 | H42: 3 | K42: =VLOOKUP(A42,MasterTutor!A:D,4,FALSE) -> Distinguished | L42: =VLOOKUP(A42,MasterTutor!A:D,3,FALSE) -> Professional | M42: =VLOOKUP(A42,MasterTutor!A:D,2,FALSE) -> Ian Plamondon
A43: Alexis Boucher | B43: 10/5/25 - 11/1/25 | C43: 0.7208 | D43: 0.9868 | E43: 1 | F43: 0.87272727 | G43: 0.95652174 | H43: 3 | K43: =VLOOKUP(A43,MasterTutor!A:D,4,FALSE) -> Distinguished | L43: =VLOOKUP(A43,MasterTutor!A:D,3,FALSE) -> Professional | M43: =VLOOKUP(A43,MasterTutor!A:D,2,FALSE) -> Ian Plamondon
A44: Alexis Boucher | B44: 11/2/25 - 11/29/25 | C44: 0.5 | D44: 0.9 | E44: 1 | F44: 0.82 | G44: 0.93 | H44: 2 | I44: 45658 | J44: 1 | K44: =VLOOKUP(A44,MasterTutor!A:D,4,FALSE) -> Distinguished | L44: =VLOOKUP(A44,MasterTutor!A:D,3,FALSE) -> Professional | M44: =VLOOKUP(A44,MasterTutor!A:D,2,FALSE) -> Ian Plamondon
A45: Alexis Boucher | B45: 5/18/25 - 6/14/25 | C45: 0.73 | D45: 0.93 | E45: 1 | F45: 0.87 | G45: 0.8 | H45: #N/A | I45: 2/3 | J45: 0.67 | K45: =VLOOKUP(A45,MasterTutor!A:D,4,FALSE) -> Distinguished | L45: =VLOOKUP(A45,MasterTutor!A:D,3,FALSE) -> Professional | M45: =VLOOKUP(A45,MasterTutor!A:D,2,FALSE) -> Ian Plamondon
A46: Alexis Boucher | B46: 6/15/25 - 7/12/25 | C46: 0.47 | D46: 0.93 | E46: 1 | F46: 0.81 | G46: 0.5 | H46: 2 | I46: 1 | J46: =I46 -> 1 | K46: =VLOOKUP(A46,MasterTutor!A:D,4,FALSE) -> Distinguished | L46: =VLOOKUP(A46,MasterTutor!A:D,3,FALSE) -> Professional | M46: =VLOOKUP(A46,MasterTutor!A:D,2,FALSE) -> Ian Plamondon
A47: Alexis Boucher | B47: 7/13/25 - 8/10/25 | C47: 0.73 | D47: 1.02 | E47: 1 | F47: 0.91 | G47: 0.71 | H47: #N/A | I47: 1 | J47: =I47 -> 1 | K47: =VLOOKUP(A47,MasterTutor!A:D,4,FALSE) -> Distinguished | L47: =VLOOKUP(A47,MasterTutor!A:D,3,FALSE) -> Professional | M47: =VLOOKUP(A47,MasterTutor!A:D,2,FALSE) -> Ian Plamondon
A48: Alexis Boucher | B48: 8/10/25 - 9/6/25 | C48: 0.74 | D48: 0.98 | E48: 1 | F48: 0.9 | G48: 0.94 | H48: 3 | I48: 5/6 | J48: 0.83 | K48: =VLOOKUP(A48,MasterTutor!A:D,4,FALSE) -> Distinguished | L48: =VLOOKUP(A48,MasterTutor!A:D,3,FALSE) -> Professional | M48: =VLOOKUP(A48,MasterTutor!A:D,2,FALSE) -> Ian Plamondon
A49: Alexis Boucher | B49: 9/7/25 - 10/4/25 | C49: 0.76 | D49: 0.99 | E49: 1 | F49: 1 | G49: 0.77 | H49: 2 | I49: 1/6 | J49: 0.17 | K49: =VLOOKUP(A49,MasterTutor!A:D,4,FALSE) -> Distinguished | L49: =VLOOKUP(A49,MasterTutor!A:D,3,FALSE) -> Professional | M49: =VLOOKUP(A49,MasterTutor!A:D,2,FALSE) -> Ian Plamondon
A50: Alexis Boucher | B50: 11/30/25 - 12/27/25 | C50: 0.36 | D50: 0.94 | E50: 0.97 | F50: 0.94 | G50: 1 | H50: 1 | K50: =VLOOKUP(A50,MasterTutor!A:D,4,FALSE) -> Distinguished | L50: =VLOOKUP(A50,MasterTutor!A:D,3,FALSE) -> Professional | M50: =VLOOKUP(A50,MasterTutor!A:D,2,FALSE) -> Ian Plamondon
A51: Alison Trumbull | B51: 10/5/25 - 11/1/25 | C51: 0.5 | D51: 0.9883 | E51: 1 | F51: 1 | G51: 1 | H51: 2 | K51: =VLOOKUP(A51,MasterTutor!A:D,4,FALSE) -> Premium | L51: =VLOOKUP(A51,MasterTutor!A:D,3,FALSE) -> Adjunct | M51: =VLOOKUP(A51,MasterTutor!A:D,2,FALSE) -> Geoff St. Marie
A52: Alison Trumbull | B52: 10/5/25 - 11/1/25 | C52: 0.5 | D52: 0.9883 | E52: 1 | F52: 1 | G52: 1 | H52: 2 | K52: =VLOOKUP(A52,MasterTutor!A:D,4,FALSE) -> Premium | L52: =VLOOKUP(A52,MasterTutor!A:D,3,FALSE) -> Adjunct | M52: =VLOOKUP(A52,MasterTutor!A:D,2,FALSE) -> Geoff St. Marie
A53: Alison Trumbull | B53: 11/2/25 - 11/29/25 | C53: 0.41 | D53: 0.9 | E53: 0.94 | F53: 1 | G53: 1 | H53: 0 | K53: =VLOOKUP(A53,MasterTutor!A:D,4,FALSE) -> Premium | L53: =VLOOKUP(A53,MasterTutor!A:D,3,FALSE) -> Adjunct | M53: =VLOOKUP(A53,MasterTutor!A:D,2,FALSE) -> Geoff St. Marie
A54: Alison Trumbull | B54: 5/18/25 - 6/14/25 | C54: 0.95 | D54: 0.86 | E54: 0.92 | F54: 0.88 | G54: 0.9 | H54: #N/A | K54: =VLOOKUP(A54,MasterTutor!A:D,4,FALSE) -> Premium | L54: =VLOOKUP(A54,MasterTutor!A:D,3,FALSE) -> Adjunct | M54: =VLOOKUP(A54,MasterTutor!A:D,2,FALSE) -> Geoff St. Marie
A55: Alison Trumbull | B55: 6/15/25 - 7/12/25 | C55: 1.15 | D55: 0.99 | E55: 0.9 | F55: 0.93 | G55: 0.82 | H55: 1 | I55: 1 | J55: =I55 -> 1 | K55: =VLOOKUP(A55,MasterTutor!A:D,4,FALSE) -> Premium | L55: =VLOOKUP(A55,MasterTutor!A:D,3,FALSE) -> Adjunct | M55: =VLOOKUP(A55,MasterTutor!A:D,2,FALSE) -> Geoff St. Marie
A56: Alison Trumbull | B56: 7/13/25 - 8/10/25 | C56: 1 | D56: 1.03 | E56: 1 | F56: 1 | G56: 0.64 | H56: 2 | K56: =VLOOKUP(A56,MasterTutor!A:D,4,FALSE) -> Premium | L56: =VLOOKUP(A56,MasterTutor!A:D,3,FALSE) -> Adjunct | M56: =VLOOKUP(A56,MasterTutor!A:D,2,FALSE) -> Geoff St. Marie
A57: Alison Trumbull | B57: 8/10/25 - 9/6/25 | C57: 1.53 | D57: 1.23 | E57: 0.97 | F57: 0.83 | G57: 1 | H57: 0 | I57: 1/1 | J57: 1 | K57: =VLOOKUP(A57,MasterTutor!A:D,4,FALSE) -> Premium | L57: =VLOOKUP(A57,MasterTutor!A:D,3,FALSE) -> Adjunct | M57: =VLOOKUP(A57,MasterTutor!A:D,2,FALSE) -> Geoff St. Marie
A58: Alison Trumbull | B58: 9/7/25 - 10/4/25 | C58: 1.08 | D58: 1.02 | E58: 0.96 | F58: 1 | G58: 1 | H58: 1 | K58: =VLOOKUP(A58,MasterTutor!A:D,4,FALSE) -> Premium | L58: =VLOOKUP(A58,MasterTutor!A:D,3,FALSE) -> Adjunct | M58: =VLOOKUP(A58,MasterTutor!A:D,2,FALSE) -> Geoff St. Marie
A59: Alison Trumbull | B59: 11/30/25 - 12/27/25 | C59: 0.37 | D59: 1.17 | E59: 0.85 | F59: 0.7 | G59: 1 | H59: 6 | I59: 1 | J59: 1 | K59: =VLOOKUP(A59,MasterTutor!A:D,4,FALSE) -> Premium | L59: =VLOOKUP(A59,MasterTutor!A:D,3,FALSE) -> Adjunct | M59: =VLOOKUP(A59,MasterTutor!A:D,2,FALSE) -> Geoff St. Marie
A60: Alli Winkelmann | B60: 5/18/25 - 6/14/25 | C60: 0.82 | D60: 0.77 | E60: 1 | F60: 1 | G60: 0.83 | H60: 3 | K60: =VLOOKUP(A60,MasterTutor!A:D,4,FALSE) -> #N/A | L60: =VLOOKUP(A60,MasterTutor!A:D,3,FALSE) -> #N/A | M60: =VLOOKUP(A60,MasterTutor!A:D,2,FALSE) -> #N/A
A61: Alli Winkelmann | B61: 6/15/25 - 7/12/25 | C61: 0.66 | D61: 0.94 | E61: 1 | F61: 0.96 | G61: 0.85 | H61: 1 | I61: 1 | J61: =I61 -> 1 | K61: =VLOOKUP(A61,MasterTutor!A:D,4,FALSE) -> #N/A | L61: =VLOOKUP(A61,MasterTutor!A:D,3,FALSE) -> #N/A | M61: =VLOOKUP(A61,MasterTutor!A:D,2,FALSE) -> #N/A
A62: Alli Winkelmann | B62: 7/13/25 - 8/10/25 | C62: 0.83 | D62: 1.05 | E62: 1 | F62: 0.94 | G62: 0.91 | H62: 2 | I62: 0 | J62: =I62 -> 0 | K62: =VLOOKUP(A62,MasterTutor!A:D,4,FALSE) -> #N/A | L62: =VLOOKUP(A62,MasterTutor!A:D,3,FALSE) -> #N/A | M62: =VLOOKUP(A62,MasterTutor!A:D,2,FALSE) -> #N/A
A63: Allison Peck | B63: 10/5/25 - 11/1/25 | C63: 0.651 | D63: 0.9844 | E63: 1 | F63: 0.94736842 | G63: 0.8 | H63: 2 | I63: 0/1 | J63: 0 | K63: =VLOOKUP(A63,MasterTutor!A:D,4,FALSE) -> Distinguished | L63: =VLOOKUP(A63,MasterTutor!A:D,3,FALSE) -> Adjunct | M63: =VLOOKUP(A63,MasterTutor!A:D,2,FALSE) -> Kristin Haase-Alvey
A64: Allison Peck | B64: 11/2/25 - 11/29/25 | C64: 0.65 | D64: 1.05 | E64: 0.97 | F64: 1 | G64: 1 | H64: 2 | K64: =VLOOKUP(A64,MasterTutor!A:D,4,FALSE) -> Distinguished | L64: =VLOOKUP(A64,MasterTutor!A:D,3,FALSE) -> Adjunct | M64: =VLOOKUP(A64,MasterTutor!A:D,2,FALSE) -> Kristin Haase-Alvey
A65: Allison Peck | B65: 5/18/25 - 6/14/25 | C65: 0 | D65: 0 | E65: 0 | F65: 0 | G65: #N/A | H65: #N/A | K65: =VLOOKUP(A65,MasterTutor!A:D,4,FALSE) -> Distinguished | L65: =VLOOKUP(A65,MasterTutor!A:D,3,FALSE) -> Adjunct | M65: =VLOOKUP(A65,MasterTutor!A:D,2,FALSE) -> Kristin Haase-Alvey
A66: Allison Peck | B66: 6/15/25 - 7/12/25 | C66: 0 | D66: 0 | E66: 0 | F66: 0 | G66: 0 | H66: #N/A | K66: =VLOOKUP(A66,MasterTutor!A:D,4,FALSE) -> Distinguished | L66: =VLOOKUP(A66,MasterTutor!A:D,3,FALSE) -> Adjunct | M66: =VLOOKUP(A66,MasterTutor!A:D,2,FALSE) -> Kristin Haase-Alvey
A67: Allison Peck | B67: 7/13/25 - 8/10/25 | C67: 0.02 | D67: 1.24 | E67: 1 | F67: 1 | G67: 1 | H67: #N/A | I67: 1 | J67: =I67 -> 1 | K67: =VLOOKUP(A67,MasterTutor!A:D,4,FALSE) -> Distinguished | L67: =VLOOKUP(A67,MasterTutor!A:D,3,FALSE) -> Adjunct | M67: =VLOOKUP(A67,MasterTutor!A:D,2,FALSE) -> Kristin Haase-Alvey
A68: Allison Peck | B68: 8/10/25 - 9/6/25 | C68: 0.24 | D68: 1.39 | E68: 1 | F68: 0.86 | G68: 0 | H68: 0 | I68: 0/1 | J68: 0 | K68: =VLOOKUP(A68,MasterTutor!A:D,4,FALSE) -> Distinguished | L68: =VLOOKUP(A68,MasterTutor!A:D,3,FALSE) -> Adjunct | M68: =VLOOKUP(A68,MasterTutor!A:D,2,FALSE) -> Kristin Haase-Alvey
A69: Allison Peck | B69: 9/7/25 - 10/4/25 | C69: 0.74 | D69: 0.73 | E69: 1 | F69: 0.87 | G69: 1 | H69: 0 | I69: 2/2 | J69: 1 | K69: =VLOOKUP(A69,MasterTutor!A:D,4,FALSE) -> Distinguished | L69: =VLOOKUP(A69,MasterTutor!A:D,3,FALSE) -> Adjunct | M69: =VLOOKUP(A69,MasterTutor!A:D,2,FALSE) -> Kristin Haase-Alvey
A70: Allison Peck | B70: 11/30/25 - 12/27/25 | C70: 0.46 | D70: 1 | E70: 0.94 | F70: 1 | G70: 1 | H70: 1 | K70: =VLOOKUP(A70,MasterTutor!A:D,4,FALSE) -> Distinguished | L70: =VLOOKUP(A70,MasterTutor!A:D,3,FALSE) -> Adjunct | M70: =VLOOKUP(A70,MasterTutor!A:D,2,FALSE) -> Kristin Haase-Alvey
A71: Amber Maldonado | B71: 10/5/25 - 11/1/25 | C71: 0.9 | D71: 1.1727 | E71: 0.85714286 | F71: 0.90140845 | G71: 0.90909091 | H71: 11 | I71: 6/7 | J71: 0.86 | K71: =VLOOKUP(A71,MasterTutor!A:D,4,FALSE) -> Advanced | L71: =VLOOKUP(A71,MasterTutor!A:D,3,FALSE) -> Professional | M71: =VLOOKUP(A71,MasterTutor!A:D,2,FALSE) -> Annelies de Groot
A72: Amber Maldonado | B72: 10/5/25 - 11/1/25 | C72: 0.9 | D72: 1.1727 | E72: 0.85714286 | F72: 0.90140845 | G72: 0.90909091 | H72: 11 | I72: 6/7 | J72: =_xlfn.TEXTBEFORE(I72, "/")/_xlfn.TEXTAFTER(I72,"/") -> 0.85714286 | K72: =VLOOKUP(A72,MasterTutor!A:D,4,FALSE) -> Advanced | L72: =VLOOKUP(A72,MasterTutor!A:D,3,FALSE) -> Professional | M72: =VLOOKUP(A72,MasterTutor!A:D,2,FALSE) -> Annelies de Groot
A73: Amber Maldonado | B73: 11/2/25 - 11/29/25 | C73: 0.66 | D73: 0.95 | E73: 0.88 | F73: 0.88 | G73: 1 | H73: 2 | I73: 45692 | J73: 0.5 | K73: =VLOOKUP(A73,MasterTutor!A:D,4,FALSE) -> Advanced | L73: =VLOOKUP(A73,MasterTutor!A:D,3,FALSE) -> Professional | M73: =VLOOKUP(A73,MasterTutor!A:D,2,FALSE) -> Annelies de Groot
A74: Amber Maldonado | B74: 5/18/25 - 6/14/25 | C74: 0.7 | D74: 1.07 | E74: 0.67 | F74: 0.93 | G74: 1 | H74: 1 | I74: 1 | J74: =I74 -> 1 | K74: =VLOOKUP(A74,MasterTutor!A:D,4,FALSE) -> Advanced | L74: =VLOOKUP(A74,MasterTutor!A:D,3,FALSE) -> Professional | M74: =VLOOKUP(A74,MasterTutor!A:D,2,FALSE) -> Annelies de Groot
A75: Amber Maldonado | B75: 6/15/25 - 7/12/25 | C75: 0.64 | D75: 1.11 | E75: 0.5 | F75: 0.88 | G75: 0.95 | H75: 1 | I75: 1 | J75: =I75 -> 1 | K75: =VLOOKUP(A75,MasterTutor!A:D,4,FALSE) -> Advanced | L75: =VLOOKUP(A75,MasterTutor!A:D,3,FALSE) -> Professional | M75: =VLOOKUP(A75,MasterTutor!A:D,2,FALSE) -> Annelies de Groot
A76: Amber Maldonado | B76: 7/13/25 - 8/10/25 | C76: 0.75 | D76: 1.07 | E76: 0.85 | F76: 0.91 | G76: 0.77 | H76: 5 | I76: 5/7 | J76: 0.71 | K76: =VLOOKUP(A76,MasterTutor!A:D,4,FALSE) -> Advanced | L76: =VLOOKUP(A76,MasterTutor!A:D,3,FALSE) -> Professional | M76: =VLOOKUP(A76,MasterTutor!A:D,2,FALSE) -> Annelies de Groot
A77: Amber Maldonado | B77: 8/10/25 - 9/6/25 | C77: 0.82 | D77: 1.1 | E77: 0.87 | F77: 0.91 | G77: 0.92 | H77: 5 | I77: 6/7 | J77: 0.86 | K77: =VLOOKUP(A77,MasterTutor!A:D,4,FALSE) -> Advanced | L77: =VLOOKUP(A77,MasterTutor!A:D,3,FALSE) -> Professional | M77: =VLOOKUP(A77,MasterTutor!A:D,2,FALSE) -> Annelies de Groot
A78: Amber Maldonado | B78: 9/7/25 - 10/4/25 | C78: 0.88 | D78: 1.06 | E78: 0.86 | F78: 0.94 | G78: 1 | H78: 4 | I78: 5/8 | J78: 0.63 | K78: =VLOOKUP(A78,MasterTutor!A:D,4,FALSE) -> Advanced | L78: =VLOOKUP(A78,MasterTutor!A:D,3,FALSE) -> Professional | M78: =VLOOKUP(A78,MasterTutor!A:D,2,FALSE) -> Annelies de Groot
A79: Amber Maldonado | B79: 11/30/25 - 12/27/25 | C79: 0 | D79: 0.05 | E79: 0 | F79: 0 | G79: 1 | H79: 0 | K79: =VLOOKUP(A79,MasterTutor!A:D,4,FALSE) -> Advanced | L79: =VLOOKUP(A79,MasterTutor!A:D,3,FALSE) -> Professional | M79: =VLOOKUP(A79,MasterTutor!A:D,2,FALSE) -> Annelies de Groot
A80: Amelia Sain | B80: 10/5/25 - 11/1/25 | C80: 0.3208 | D80: 1.0877 | E80: 1 | F80: 0.82608696 | G80: 0.14285714 | H80: 1 | I80: 0/1 | J80: 0 | K80: =VLOOKUP(A80,MasterTutor!A:D,4,FALSE) -> Premium | L80: =VLOOKUP(A80,MasterTutor!A:D,3,FALSE) -> Professional | M80: =VLOOKUP(A80,MasterTutor!A:D,2,FALSE) -> Jessica Milner
A81: Amelia Sain | B81: 11/2/25 - 11/29/25 | C81: 0.49 | D81: 1.18 | E81: 1 | F81: 1 | G81: 0.33 | H81: 1 | I81: 0/2 | J81: 0 | K81: =VLOOKUP(A81,MasterTutor!A:D,4,FALSE) -> Premium | L81: =VLOOKUP(A81,MasterTutor!A:D,3,FALSE) -> Professional | M81: =VLOOKUP(A81,MasterTutor!A:D,2,FALSE) -> Jessica Milner
A82: Amelia Sain | B82: 5/18/25 - 6/14/25 | C82: 0.92 | D82: 1.33 | E82: 1 | F82: 0.98 | G82: 0.5 | H82: 2 | I82: 0 | J82: =I82 -> 0 | K82: =VLOOKUP(A82,MasterTutor!A:D,4,FALSE) -> Premium | L82: =VLOOKUP(A82,MasterTutor!A:D,3,FALSE) -> Professional | M82: =VLOOKUP(A82,MasterTutor!A:D,2,FALSE) -> Jessica Milner
A83: Amelia Sain | B83: 6/15/25 - 7/12/25 | C83: 0.56 | D83: 1.4 | E83: 1 | F83: 0.92 | G83: 0.43 | H83: 2 | I83: 0 | J83: =I83 -> 0 | K83: =VLOOKUP(A83,MasterTutor!A:D,4,FALSE) -> Premium | L83: =VLOOKUP(A83,MasterTutor!A:D,3,FALSE) -> Professional | M83: =VLOOKUP(A83,MasterTutor!A:D,2,FALSE) -> Jessica Milner
A84: Amelia Sain | B84: 7/13/25 - 8/10/25 | C84: 0.51 | D84: 1.36 | E84: 1 | F84: 0.94 | G84: 0.53 | H84: 2 | K84: =VLOOKUP(A84,MasterTutor!A:D,4,FALSE) -> Premium | L84: =VLOOKUP(A84,MasterTutor!A:D,3,FALSE) -> Professional | M84: =VLOOKUP(A84,MasterTutor!A:D,2,FALSE) -> Jessica Milner
A85: Amelia Sain | B85: 8/10/25 - 9/6/25 | C85: 0.72 | D85: 1.11 | E85: 1 | F85: 0.75 | G85: 0.15 | H85: 1 | I85: 0/4 | J85: 0 | K85: =VLOOKUP(A85,MasterTutor!A:D,4,FALSE) -> Premium | L85: =VLOOKUP(A85,MasterTutor!A:D,3,FALSE) -> Professional | M85: =VLOOKUP(A85,MasterTutor!A:D,2,FALSE) -> Jessica Milner
A86: Amelia Sain | B86: 9/7/25 - 10/4/25 | C86: 0.57 | D86: 1.17 | E86: 1 | F86: 0.86 | G86: 0 | H86: 1 | I86: 0/1 | J86: 0 | K86: =VLOOKUP(A86,MasterTutor!A:D,4,FALSE) -> Premium | L86: =VLOOKUP(A86,MasterTutor!A:D,3,FALSE) -> Professional | M86: =VLOOKUP(A86,MasterTutor!A:D,2,FALSE) -> Jessica Milner
A87: Amelia Sain | B87: 11/30/25 - 12/27/25 | C87: 0.26 | D87: 0.88 | E87: 1 | F87: 0.94 | G87: 0.7 | H87: 2 | K87: =VLOOKUP(A87,MasterTutor!A:D,4,FALSE) -> Premium | L87: =VLOOKUP(A87,MasterTutor!A:D,3,FALSE) -> Professional | M87: =VLOOKUP(A87,MasterTutor!A:D,2,FALSE) -> Jessica Milner
A88: Amy Kim | B88: 11/30/25 - 12/27/25 | C88: 0 | D88: 0 | E88: 0 | F88: 0 | G88: 0 | H88: 0 | K88: =VLOOKUP(A88,MasterTutor!A:D,4,FALSE) -> #N/A | L88: =VLOOKUP(A88,MasterTutor!A:D,3,FALSE) -> #N/A | M88: =VLOOKUP(A88,MasterTutor!A:D,2,FALSE) -> #N/A
A89: Ana Heiser | B89: 10/5/25 - 11/1/25 | C89: 0.5958 | D89: 1.1349 | E89: 0.97142857 | F89: 0.69565217 | G89: 1 | H89: 0 | I89: 6/6 | J89: 1 | K89: =VLOOKUP(A89,MasterTutor!A:D,4,FALSE) -> Distinguished | L89: =VLOOKUP(A89,MasterTutor!A:D,3,FALSE) -> Professional | M89: =VLOOKUP(A89,MasterTutor!A:D,2,FALSE) -> Kristin Haase-Alvey
A90: Ana Heiser | B90: 11/2/25 - 11/29/25 | C90: 0.56 | D90: 1.01 | E90: 1 | F90: 0.84 | G90: 0.89 | H90: 2 | I90: 45690 | J90: 1 | K90: =VLOOKUP(A90,MasterTutor!A:D,4,FALSE) -> Distinguished | L90: =VLOOKUP(A90,MasterTutor!A:D,3,FALSE) -> Professional | M90: =VLOOKUP(A90,MasterTutor!A:D,2,FALSE) -> Kristin Haase-Alvey
A91: Ana Heiser | B91: 5/18/25 - 6/14/25 | C91: 0.69 | D91: 0.93 | E91: 0.98 | F91: 1 | G91: 0.73 | H91: 6 | I91: 1 | J91: =I91 -> 1 | K91: =VLOOKUP(A91,MasterTutor!A:D,4,FALSE) -> Distinguished | L91: =VLOOKUP(A91,MasterTutor!A:D,3,FALSE) -> Professional | M91: =VLOOKUP(A91,MasterTutor!A:D,2,FALSE) -> Kristin Haase-Alvey
A92: Ana Heiser | B92: 6/15/25 - 7/12/25 | C92: 0.74 | D92: 1.03 | E92: 0.96 | F92: 0.98 | G92: 0.83 | H92: 7 | I92: 1 | J92: =I92 -> 1 | K92: =VLOOKUP(A92,MasterTutor!A:D,4,FALSE) -> Distinguished | L92: =VLOOKUP(A92,MasterTutor!A:D,3,FALSE) -> Professional | M92: =VLOOKUP(A92,MasterTutor!A:D,2,FALSE) -> Kristin Haase-Alvey
A93: Ana Heiser | B93: 7/13/25 - 8/10/25 | C93: 0.76 | D93: 0.91 | E93: 0.96 | F93: 0.97 | G93: 0.89 | H93: 3 | I93: 4/5 | J93: 0.8 | K93: =VLOOKUP(A93,MasterTutor!A:D,4,FALSE) -> Distinguished | L93: =VLOOKUP(A93,MasterTutor!A:D,3,FALSE) -> Professional | M93: =VLOOKUP(A93,MasterTutor!A:D,2,FALSE) -> Kristin Haase-Alvey
A94: Ana Heiser | B94: 8/10/25 - 9/6/25 | C94: 0.82 | D94: 0.99 | E94: 0.98 | F94: 0.96 | G94: 1 | H94: 7 | I94: 3/4 | J94: 0.75 | K94: =VLOOKUP(A94,MasterTutor!A:D,4,FALSE) -> Distinguished | L94: =VLOOKUP(A94,MasterTutor!A:D,3,FALSE) -> Professional | M94: =VLOOKUP(A94,MasterTutor!A:D,2,FALSE) -> Kristin Haase-Alvey
A95: Ana Heiser | B95: 9/7/25 - 10/4/25 | C95: 0.81 | D95: 1.06 | E95: 0.98 | F95: 0.84 | G95: 1 | H95: 11 | I95: 0/1 | J95: 0 | K95: =VLOOKUP(A95,MasterTutor!A:D,4,FALSE) -> Distinguished | L95: =VLOOKUP(A95,MasterTutor!A:D,3,FALSE) -> Professional | M95: =VLOOKUP(A95,MasterTutor!A:D,2,FALSE) -> Kristin Haase-Alvey
A96: Ana Heiser | B96: 11/30/25 - 12/27/25 | C96: 0.32 | D96: 0.86 | E96: 0.97 | F96: 0.7 | G96: 1 | H96: 0 | I96: 1 | J96: 1 | K96: =VLOOKUP(A96,MasterTutor!A:D,4,FALSE) -> Distinguished | L96: =VLOOKUP(A96,MasterTutor!A:D,3,FALSE) -> Professional | M96: =VLOOKUP(A96,MasterTutor!A:D,2,FALSE) -> Kristin Haase-Alvey
A97: Andres Jarquin | B97: 10/5/25 - 11/1/25 | C97: 1.0792 | D97: 1.0822 | E97: 0.9869281 | F97: 0.93478261 | G97: 0.26666667 | H97: 12 | I97: 1/10 | J97: 0.1 | K97: =VLOOKUP(A97,MasterTutor!A:D,4,FALSE) -> Advanced | L97: =VLOOKUP(A97,MasterTutor!A:D,3,FALSE) -> Professional | M97: =VLOOKUP(A97,MasterTutor!A:D,2,FALSE) -> Ian Plamondon
A98: Andres Jarquin | B98: 11/2/25 - 11/29/25 | C98: 1.03 | D98: 0.98 | E98: 0.99 | F98: 0.97 | G98: 0.16 | H98: 17 | I98: 0/1 | J98: 0 | K98: =VLOOKUP(A98,MasterTutor!A:D,4,FALSE) -> Advanced | L98: =VLOOKUP(A98,MasterTutor!A:D,3,FALSE) -> Professional | M98: =VLOOKUP(A98,MasterTutor!A:D,2,FALSE) -> Ian Plamondon
A99: Andres Jarquin | B99: 9/7/25 - 10/4/25 | C99: 0.88 | D99: 1.08 | E99: 0.99 | F99: 0.97 | G99: 0.17 | H99: 9 | I99: 0/10 | J99: 0 | K99: =VLOOKUP(A99,MasterTutor!A:D,4,FALSE) -> Advanced | L99: =VLOOKUP(A99,MasterTutor!A:D,3,FALSE) -> Professional | M99: =VLOOKUP(A99,MasterTutor!A:D,2,FALSE) -> Ian Plamondon
A100: Andres Jarquin | B100: 11/30/25 - 12/27/25 | C100: 0.78 | D100: 0.84 | E100: 0.97 | F100: 1 | G100: 0.18 | H100: 8 | K100: =VLOOKUP(A100,MasterTutor!A:D,4,FALSE) -> Advanced | L100: =VLOOKUP(A100,MasterTutor!A:D,3,FALSE) -> Professional | M100: =VLOOKUP(A100,MasterTutor!A:D,2,FALSE) -> Ian Plamondon
...

Sheet ProgressUpdateEmails
A1: update_id | B1: sent_at | C1: tutor | D1: team | E1: course_id | F1: student_name | G1: body | H1: AI Score
A2: 10918864 | B2: 45991 | C2: Christine Santos | D2: Team Cross | E2: 85148 | F2: Lev Wechselblatt | G2: Hi Daniella, I hope youâ€™re doing well! I wanted to share an update on Levâ€™s recent progress as he prepares for the ACT. During our last session, Lev and I reviewed the questions he missed from his recent practice test. Iâ€™m happy to report that he showed considerable improvement in the â€œstudent as editorâ€ questionsâ€”an area weâ€™ve been focusing on, and itâ€™s wonderful to see that our hard work is paying off. Levâ€™s continued progress in this area will serve him well on the actual test. We also identified several more questions, particularly in the science section and the English sectionâ€™s punctuation items, that Lev can easily capture for additional points. To support this, my recommendation is that we begin incorporating more mixed review, focusing on strategies for different science passages and targeted practice with punctuation rules in the English section. Weâ€™ll also be building in timing limits during our practice sessions to help Lev balance his time effectively and minimize rushing or simple mistakes. Despite a few missed questions, Lev performed very well on this last practice test, and Iâ€™m confident that he has all the skills needed to succeed on test dayâ€”itâ€™s just a matter of bringing everything together. If you have any questions or would like to discuss Levâ€™s progress further, please feel free to reach out by email or text. Iâ€™m always happy to help! Thank you, and I look forward to continuing to support Lev! Christine S. christine.santos@revolutionprep.com +19415649546 | H2: 3
A3: 10918868 | B3: 45991 | C3: Kristen Luigart | D3: Team Plamondon | E3: 89581 | F3: Yasmine Hammami | G3: Good evening Kirsten, First off, it was lovely to meet Yasmine this week, she's such a passionate and vibrant young lady, and I wanted to say that she was an absolute pleasure to work with! Yasmine approached the whole essay editing process with maturity and impressive self-awareness. We started this week's session by reading through all of Yasmineâ€™s PIQs, and I provided in-text comments on each. However, we ended up spending majority of our time focusing on the PIQ about her NYT program experience and her personal connection to communication, journalism, and journalistic integrity. When we began, this PIQ had strong ideas but lacked direction and clarity. The opening framed her identity as a â€œglobal writerâ€ and referenced AP English, Mock Trial, and her New York Times coursework equallyâ€”accomplishments that are truly impressive, but in the original draft appeared more as a list than a cohesive, compelling story. The essay needed specificity, stronger organization, and more â€œshow, donâ€™t tell.â€ Together, we reshaped the PIQ into a much more focused and powerful narrative. Yasmine now shares a concrete story about her personal passion for using journalism and communication to correct biased media coverage of Tunisia and the world. This shift allowed her to highlight meaningful experiences and connect them directly to her academic and professional goals. The revised essay includes vivid, authentic detailsâ€”such as using PeopleFinder, interviewing techniques, and NYT archival researchâ€”that demonstrate her initiative, curiosity, and early commitment to journalistic integrity. The new structure paints a clear picture of the work she has done and shows readers exactly why her passion is real and hard-earned. Yasmine made excellent progress in just one session, and I believe continuing to refine any college essays with consistent guidance will only make her applications stronger. I recommend meeting once weekly for one hour as needed to support any additional revisions or new essays she may need to complete for her last few applications. If youâ€™d like to discuss Yasmineâ€™s work or next steps, Iâ€™d be happy to schedule a Zoom or phone call at your convenience. Happy Thanksgiving!Â Kristen Luigart, M.Ed., M.A. kristen.luigart@revolutionprep.com +13018205071 | H3: 4
A4: 10918889 | B4: 45991 | C4: Kristen Luigart | D4: Team Plamondon | E4: 83525 | F4: Loui Takahashi | G4: Good Morning Ippei, I'm writing to give you a bit of a wrap up of all the work Loui and I have done in her tutoring sessions so far. Loui's been working extremely hard (especially with all she has going on in school and out), and her ambitious and passionate nature reflects in her writing and intelligence. Together, we have now completed Loui's personal essay, as well as her supplemental essays for Yale, the University of Vermont, Tufts, and -- most recently -- UC Berkeley, which we just finalized with only a little time to spare. Despite the tight timeline, her Berkeley essays turned out excellent. Loui's writing has a strong, innate, sense of storytelling, and a compelling voice to begin with, so working with her on her essays has really been about giving more immediacy and vibrancy to the works. (And sometimes helping her find the motivation to be passionate about some truly awful prompts! ;3) Throughout all the essays, we have focused on strengthening Loui's language and composition to create more compelling narrative flow, express more passion, and illustrate with greater clarity. The key to a good college application essay is being able to use only a couple hundred words to become a fully-fleshed out being to the numbed essay readers at university admissions. With hundreds of thousands of students applying to schools every year, essay readers tend to zone out quickly when essays are repetitive or rote. (I have personal experience with this from being the chair of admissions for UVA's honors dorm, Brown College, which had its own rigorous application essay process.) Therefore, to break through the monotonous repetition of the usual accomplishment lists draped in prose disguised as essays, a student must not only answer their prompts intelligently -- but compellingly, in order to rise above the simple 'fulfilled requirement' stack. I am confident that the essays Loui has brought from this program have all had that spark, and that they use it effectively to highlight how impressive and multifaceted Loui is as an applicant. A good example of this editing process can be seen in how, when we first reviewed Loui's Berkeley drafts, she and I both found them to come across as flat and lacking passion. The prompt, itself, was relatively dry, and without finding a way to feel passionate about the subject, Loui's work came out as simply informative and somewhat distanced. The essays read more like reports than personal reflections. Over several rounds of revision, Loui transformed them all into essays that are far more authentic, vital, and emotionally grounded. For example, the new essay on social mediaâ€™s impact on Loui's life, and her subsequent rejection of it, presents compelling statisticsâ€”such as 5.3 billion selfies are taken per day â€” that highlight Loui's wisdom in learning how to "put down the light-up brick". These striking facts, and the additional comments on the human history of appearance, helped anchor Loui's narrative in something both memorable and meaningful. With Berkeley completed, our next priority is Johns Hopkins. Brainstorming for its essays is Loui's homework for our next session on December 13. After that, we will continue on with her essays for Bowdoin, CMU, and the University of Chicago. To ensure Loui stays comfortably ahead of all deadlines, and maintains her strong momentum, I recommend meeting at least once a week for an hour until all remaining essays are completed. (Ideally, therefore, they will be finished well before their due dates). If youâ€™d like to discuss Louiâ€™s progress or upcoming plans, I would be happy to schedule a Zoom or phone call at your convenience. Warm regards, and Happy Thanksgiving! Kristen Luigart, M.Ed., M.A. Kristen.Luigart@Revolutionprep.com (301)*20-5071 | H4: 4
A5: 10918896 | B5: 45991 | C5: Myles Oldroyd | D5: Team Plamondon | E5: 90236 | F5: Brooks Main | G5: Dear Clayton, Itâ€™s been great working with you and Brooks over the past two months. As we prepare for Brooks's upcoming December SAT, I wanted to share some updates and information about what to expect. I have seen significant improvements in Brooks's two passage reading, measures of central tendency, main ideas, and interpreting equations. They have shown consistent progress in homework and practice tests. This consistent improvement has been evident in a new high score on a practice test of 1440. For this exam, our goal is 1500. While we cannot guarantee a specific score, we have worked diligently towards this goal through B-PRIMES, Title 10, and IESME. It's important to consider the impact of the test zone on Brooks's performance. Ensuring a good night's sleep throughout the week leading up to the test is crucial, as just the night before isn't enough. We have also discussed strategies to manage test anxiety, which can impact scores. I am looking forward to continuing to work with Brooks after the test so that we can work towards further improvements on the SAT. I recommend maintaining at least one session a week until Brooks is happy with his score in order to help them achieve their goals. Please let me know if you have any questions or if there are any adjustments you would like to make to our plan. Iâ€™m also able to schedule a time to talk by phone if that would be helpful. I am happy to support Brooks in their continued academic journey. Thank you and stay safe, Myles O. myles.oldroyd@revolutionprep.com +15304434701 | H5: 3
A6: 10918902 | B6: 45991 | C6: Myles Oldroyd | D6: Team Plamondon | E6: 83644 | F6: Reese Migdal | G6: Dear Kristina, I hope youâ€™re doing well. I wanted to share an update on Reeseâ€™s progress over the past two months and outline our plan moving forward. Over the last two months, Reese has shown meaningful improvement in command of textual evidence, central ideas and details, and trigonometric identities.While working on precalc, Reese seemed to grasp how to view trigonometric identities as a puzzle to solve rather than an annoyance to complete. Our goals over the next phase of instruction include continuing to build his SAT readiness, deepening mastery of reading skills, and ensuring Reese feels confident applying these skills independently. To support this, I recommend regular sessions of at least once a week to prepare for the SAT and keep up with his math course. In the coming sessions, I plan to focus on the reading portion of the SAT including reading comprehension and data analysis, while continuing to reinforce previous learning targets. If you have any questions or if there are adjustments youâ€™d like to make to our plan, please feel free to reach out. Iâ€™m happy to schedule a call if that would be helpful. Thank you for your continued partnership. Itâ€™s a pleasure working with Reese and supporting his academic growth. Thank you and stay safe, Myles O. myles.oldroyd@revolutionprep.com +15304434701 | H6: 3
A7: 10918905 | B7: 45991 | C7: Tea Stewart | D7: Team Haase-Alvey | E7: 81932 | F7: Oscar Anguiano | G7: Hi Oscar, I hope you are having a great fall season. Itâ€™s been wonderful working with you and Oscar over the past couple of months. I wanted to take a moment to share some of the progress weâ€™ve made so far and outline my thoughts moving forward. I have seen significant improvements in Oscarâ€™s understanding and application of graph transformations, particularly with horizontal shifts. Over the semester, he has become much more confident identifying when a function is moving left or right and applying that knowledge accurately in practice problems. In addition, Oscar has shown strong growth in his work with similar triangle ratios. He consistently sets up correct proportions and demonstrates a solid understanding of how corresponding sides relate, which has been a highlight of his progress. His willingness to ask questions and revisit challenging problems has been one of the biggest contributors to this growth, and Iâ€™ve seen his confidence increase as a result. Our current short-term goals for Oscar include strengthening his understanding of function notation, learning to distinguish between stretches and compressions, and accurately identifying reflections across the x- and y-axis. In geometry, short-term goals also include improving his ability to solve proportions that lead to quadratic equations and deepening his understanding of geometric means within triangle relationships. The overall goal remains building Oscarâ€™s confidence and mastery in algebra and geometry so he feels prepared and capable in his math coursework. Based on Oscarâ€™s progress, I suggest we continue with our weekly 60-minute sessions moving forward. Overall, Oscar has worked hard throughout the semester, and his progress and grades reflects that effort. I look forward to continuing to support his growth in these areas. Please feel free to reach out if you have any questions or would like additional updates. Tea S. tea.stewart@revolutionprep.com +17193017642 | H7: 3
A8: 10918906 | B8: 45991 | C8: Tea Stewart | D8: Team Haase-Alvey | E8: 78245 | F8: Noor El-Helw | G8: Hi Dania, I hope you are having a great fall season. Itâ€™s been wonderful working with you and Noor over the past couple of months. I wanted to take a moment to share some of the progress weâ€™ve made so far and outline my thoughts moving forward. I have seen significant improvements in Noorâ€™s understanding and setup of improper integrals. She has consistently demonstrated the ability to recognize when an integral requires limits or a domain adjustment, and her accuracy in forming the correct limit expressions has strengthened throughout the semester. Noor has also done well with tangent line equations for parametric functions, showing confidence in applying derivatives correctly to construct linear approximations. Additionally, she has shown strong mastery in working with speed and velocity vectors of parametric functions, as well as selecting appropriate radian values to construct polar coordinate tables. In integration, Noor has done excellent work eliminating factors to determine unknown constants for partial fractions, a skill that has noticeably improved her efficiency and accuracy. Noor continues to work on several more advanced skills appropriate for Calculus BC. We will focus on strengthening her ability to determine when an improper integral converges or diverges, as well as developing clearer instincts on when extended Lâ€™HÃ´pitalâ€™s Rule is appropriate. She will also benefit from more targeted practice finding vertical and horizontal tangent lines for parametric curves. In polar coordinates, Noorâ€™s next steps include improving her graphing of polar functions with negative r-values and building confidence in interpreting their directional behavior. For integration, she will continue to work on simplifying improper rational expressions before applying partial fractions. We will also devote additional time to solving for t in complex trigonometric equations, an area that will benefit from repeated structured practice. Our current short-term goals for Noor include strengthening her convergence/divergence reasoning, mastering tangent line behavior in parametric curves, and improving clarity with both polar graphing techniques and trigonometric equation solving. The overall goal remains to build Noorâ€™s confidence and mastery across all BC topics so she feels fully prepared for assessments and the AP Exam. Based on Noorâ€™s progress, I recommend maintaining our current schedule of two 60-minute sessions to support steady development as we move into more challenging units. Noor has shown consistent effort throughout the semester, and her progress reflects that dedication. I look forward to continuing to support her growth in these areas. Please feel free to reach out if you have any questions or would like additional updates. Tea S. tea.stewart@revolutionprep.com +17193017642 | H8: 4
A9: 10918907 | B9: 45991 | C9: Tea Stewart | D9: Team Haase-Alvey | E9: 91642 | F9: Gavin Gardner | G9: Hi Shanna, I hope you are having a great fall season. Itâ€™s been wonderful working with you and Gavin over the past couple of months. I wanted to take a moment to share some of the progress weâ€™ve made so far and outline my thoughts moving forward. I have seen improvements in Gavinâ€™s ability to solve systems of equations. He has become more confident setting up equations, choosing appropriate methods, and checking his work for accuracy. Gavin has also done well using the Desmos linear regression formula to analyze linear relationships and interpret results correctly, which has strengthened his problem-solving skills in algebra. In English, he has shown strong progress identifying introductory phrases, demonstrating a clearer understanding of sentence structure and grammatical components. Moving forward, Gavin will continue working on several key areas. In math, he will benefit from becoming more comfortable with the functions and tools embedded within Desmos, which will help him work more efficiently and accurately during assignments. In writing, he will continue developing his ability to combine two complete sentences using the three correct methodsâ€”comma + coordinating conjunction, semicolon, or a period. Improving consistency with these skills will support his clarity and correctness in written communication. Additionally, we will focus on building stronger habits around homework completion, especially avoiding last-minute work so he can focus on quality and comprehension. Our current short-term goals for Gavin include strengthening his command of the three ways to combine complete sentences, improving his use of Desmos tools, and establishing consistent homework routines. The overall goal remains building Gavinâ€™s confidence, accuracy, and independence across his math and writing tasks. Based on Gavinâ€™s progress, I recommend we maintain our current schedule of weekly 60-minute sessions to support steady growth while continuing to reinforce foundational skills. I look forward to continuing to support his growth in these areas. Please feel free to reach out if you have any questions or would like additional updates. Tea S. tea.stewart@revolutionprep.com +17193017642 | H9: 3
A10: 10918908 | B10: 45991 | C10: Tea Stewart | D10: Team Haase-Alvey | E10: 94355 | F10: Sanaa Dighe | G10: Hi Saurabh, I'm excited to reach out to celebrate Sanaaâ€™s amazing progress. Sanaa has worked diligently this semester, and as a result, she scored a 1270 on her PSAT. This is a strong milestone that reflects her effort, consistency, and growth across both math and English skills. I am so proud of the work she has put in and the confidence she is building. Sanaa has shown clear strengths in several areas. In math, she has demonstrated strong familiarity with Desmos functions, has been successful solving for constants of linear functions using Desmos when given points, and has shown solid understanding of special angle relationships involving parallel lines. She has also excelled at setting up equations to determine unknown side lengths and angle measures, as well as setting up proportions for similar shapes. Additionally, she consistently extracts key information from a variety of math problems, which is a major skill for both the SAT and her math coursework. In English, Sanaa has shown strong command of identifying conjunctions, distinguishing between independent and dependent clauses, and applying apostrophe rules accurately. These foundational grammar skills have greatly helped her improve her sentence structure and overall writing clarity. While we are celebrating these successes, there is still targeted work ahead as Sanaa continues preparing for upcoming assessments and the SAT. In math, she will continue improving her approach to multi-condition word problems, strengthening her understanding of similar triangle properties, and finding unknown side lengths. We will also continue reinforcing her understanding of trigonometric relationships so she does not mix up when to use sine, cosine, or tangent. Next session, we will begin working more deeply on triangle trigonometry to extend these skills. In English, Sanaa will continue practicing the three ways to combine two complete sentences, improving her understanding of comma rules, and strengthening her ability to distinguish independent and dependent clauses in more complex sentence structures. She will also benefit from additional practice with transition questions, specifically determining whether clauses are in agreement or disagreement, and from eliminating punctuation-based answer choices more strategically. I am looking forward to continuing to work with Sanaa toward further improvements. I recommend maintaining our current 60 minute weekly sessions so she can continue steady progress toward her next goals, particularly as we begin deeper SAT-level grammar and math strategy work. Sanaa has worked incredibly hard, and her results truly reflect that effort. Iâ€™m excited to keep supporting her as she moves toward her next academic milestones. Please reach out if you have additional questions. Tea S. tea.stewart@revolutionprep.com +17193017642 | H10: 4
A11: 10918913 | B11: 45991 | C11: Myles Oldroyd | D11: Team Plamondon | E11: 90993 | F11: Nicolas Dellarocca | G11: Dear Chris and Kim, Itâ€™s been great working with you and Nico over the past month. As we prepare for Nico's upcoming December SAT, I wanted to share some updates and information about what to expect. I have seen significant improvements in Nico's transitions, measures of central tendency, and word problems. They have shown consistent progress in homework completion, practice tests, and confidence. This consistent improvement has been evident in their continued growth and steady performance across recent practice tests. For this exam, our goal is 1500. While we cannot guarantee a specific score, we have worked diligently towards this goal through IESME, B-PRIMES, and Title 10. It's important to consider the impact of the test zone on Nico's performance. Ensuring a good night's sleep throughout the week leading up to the test is crucial, as just the night before isn't enough. We have also discussed strategies to manage test anxiety, which can impact scores. I am looking forward to hearing how Nico performs on this test. Nico currently has one hour remaining in his account that is unscheduled. Please let me know if you have any questions or if there are any adjustments you would like to make to our plan. Iâ€™m also able to schedule a time to talk by phone if that would be helpful. I am happy to support Nico in their continued academic journey. Thank you and stay safe, Myles O. myles.oldroyd@revolutionprep.com +15304434701 | H11: 1
A12: 10918921 | B12: 45991 | C12: Jason Noble | D12: Team Haase-Alvey | E12: 94893 | F12: Abel Uriostegui | G12: Dear Brittney Uriostegui, I hope you are having a great fall season. Itâ€™s been great working with you and Abel over the past couple of months. I wanted to touch base to share some of the progress weâ€™ve made so far and share my thoughts on the plan moving forward. I have seen significant improvements in Abelâ€™s understanding of decimals, fractions, and foundational algebraic skills. He has shown consistent progress in multiplying and dividing decimals, working with exponents and radicals, solving one-step equations (both standalone and in word problems), and applying operations with positive and negative numbers. This consistent improvement has been evident in his ability to work through increasingly challenging problems, his accuracy with proportional relationships and factors, and his successful transition from proportions into multi-step multiplication, including multiplying within the hundreds. Our current short-term goals for Abel include reinforcing his proportional reasoning, strengthening his fluency with operations involving rational numbers, and continuing to develop his confidence as we introduce more advanced pre-algebra concepts. The overall goal remains keeping him working at an advanced level and preparing him for continued success in higher-level math. Based on Abelâ€™s progress, I recommend continuing to meet for one hour each weekâ€”either as two 30-minute sessions on Monday and Wednesday or as a single one-hour session. This schedule supports steady, accelerated growth and gives Abel consistent practice as he advances into more rigorous material. If you'd like to continue working together on achieving these goals, you can easily use this link to add the hours to your account today: https://my.revolutionprep.com/s/7cHIgWpgJo. Please let me know if you have any questions or if there are any adjustments you would like to make to our plan. Iâ€™m happy to schedule a time to talk by phone if that would be helpful. I look forward to supporting Abel in his continued academic journey. Best regards, Jason N. jason.noble@revolutionprep.com +12162627470 | H12: 4
A13: 10918923 | B13: 45991 | C13: Jason Noble | D13: Team Haase-Alvey | E13: 88830 | F13: Noah Antonio Magana | G13: Dear Tricia Marie Nepomuceno, I hope you are having a great fall season. Itâ€™s been great working with you and Noah over the past couple of months. I wanted to touch base to share some of the progress weâ€™ve made so far and share my thoughts on the plan moving forward. I have seen significant improvements in Noahâ€™s punctuation, grammar, and ability to complete and edit his school assignments. He has shown consistent progress in working through his homework, reviewing grammar concepts, practicing journaling, and building his confidence with both reading and writing tasks. This consistent improvement has been evident in his increased independence with school assignments, his completion of editing practice, and his engagement in introductory Python coding lessons. Our current short-term goals for Noah include continuing to complete school assignments on time, strengthening his reading comprehension through summary writing, and further developing his narrative and academic writing clarity. The overall goal remains improving his confidence and skills in writing, reading comprehension, andâ€”if he choosesâ€”his progression through Python coding units. Based on Noahâ€™s progress, I recommend continuing to meet once a week for one hour to focus on his school assignments or, when he has no homework, to practice reading passages and summarizing them to further improve his writing skills. If he would like to continue learning Python, we can meet once a week for that as well, though those sessions should remain separate to keep each focus area structured and effective. If you'd like to continue working together on achieving these goals, you can redeem more credits through your Bright Horizon's portal. After you redeem your credits, you will receive an email from Revolution Prep to add the hours to your account. Please let me know if you have any questions or if there are any adjustments you would like to make to our plan. Iâ€™m happy to schedule a time to talk by phone if that would be helpful. I look forward to supporting Noah in his continued academic journey. Best regards, Jason N. jason.noble@revolutionprep.com +12162627470 | H13: 4
... A5006: 10862381 | B5006: 45921 | C5006: Zoe Shanley | D5006: Team Plamondon | E5006: 91769 | F5006: Michael Gumino | G5006: Hi Tiffany and Michael, I hope you are well. I wanted to touch base on Michael's progress and discuss the plan moving forward since his test date is coming up quickly. Michael has shown significant improvement in answering questions efficiently in session. He is improving his grammar and punctuation skills as well as fine tuning his already well rounded math skills. I really appreciate the work he has put into our sessions and outside our sessions. I had Michael take a practice exam recently in which he scored an 1140. I am proud of his work; however, with the SAT date coming nearer, and us only having two hours left of sessions scheduled before the test, I wanted to reach out with some thoughts on what I think we should do to get him to the score he wants. In these last two weeks leading up to the test, I would like to recommend that he schedule more hours with me if this is something that works for his availability. Michael is a great student, and he absolutely has the ability to score well on the SAT. I would ideally recommend 3-4 this week and 3-4 hours next week before the test date to get him to his goal. If this is not a feasible schedule adjustment, I am happy to talk more about what we can do to get Michael to his goal. If you would like to discuss more, I am happy to schedule a phone or zoom call. Best, Zoe Zoe S. zoe.shanley@revolutionprep.com +16362488201 | H5006: 3
A5007: 10918864 | B5007: 45991 | C5007: Christine Santos | D5007: Team Cross | E5007: 85148 | F5007: Lev Wechselblatt | G5007: Hi Daniella, I hope youâ€™re doing well! I wanted to share an update on Levâ€™s recent progress as he prepares for the ACT. During our last session, Lev and I reviewed the questions he missed from his recent practice test. Iâ€™m happy to report that he showed considerable improvement in the â€œstudent as editorâ€ questionsâ€”an area weâ€™ve been focusing on, and itâ€™s wonderful to see that our hard work is paying off. Levâ€™s continued progress in this area will serve him well on the actual test. We also identified several more questions, particularly in the science section and the English sectionâ€™s punctuation items, that Lev can easily capture for additional points. To support this, my recommendation is that we begin incorporating more mixed review, focusing on strategies for different science passages and targeted practice with punctuation rules in the English section. Weâ€™ll also be building in timing limits during our practice sessions to help Lev balance his time effectively and minimize rushing or simple mistakes. Despite a few missed questions, Lev performed very well on this last practice test, and Iâ€™m confident that he has all the skills needed to succeed on test dayâ€”itâ€™s just a matter of bringing everything together. If you have any questions or would like to discuss Levâ€™s progress further, please feel free to reach out by email or text. Iâ€™m always happy to help! Thank you, and I look forward to continuing to support Lev! Christine S. christine.santos@revolutionprep.com +19415649546
A5008: 10918868 | B5008: 45991 | C5008: Kristen Luigart | D5008: Team Plamondon | E5008: 89581 | F5008: Yasmine Hammami | G5008: Good evening Kirsten, First off, it was lovely to meet Yasmine this week, she's such a passionate and vibrant young lady, and I wanted to say that she was an absolute pleasure to work with! Yasmine approached the whole essay editing process with maturity and impressive self-awareness. We started this week's session by reading through all of Yasmineâ€™s PIQs, and I provided in-text comments on each. However, we ended up spending majority of our time focusing on the PIQ about her NYT program experience and her personal connection to communication, journalism, and journalistic integrity. When we began, this PIQ had strong ideas but lacked direction and clarity. The opening framed her identity as a â€œglobal writerâ€ and referenced AP English, Mock Trial, and her New York Times coursework equallyâ€”accomplishments that are truly impressive, but in the original draft appeared more as a list than a cohesive, compelling story. The essay needed specificity, stronger organization, and more â€œshow, donâ€™t tell.â€ Together, we reshaped the PIQ into a much more focused and powerful narrative. Yasmine now shares a concrete story about her personal passion for using journalism and communication to correct biased media coverage of Tunisia and the world. This shift allowed her to highlight meaningful experiences and connect them directly to her academic and professional goals. The revised essay includes vivid, authentic detailsâ€”such as using PeopleFinder, interviewing techniques, and NYT archival researchâ€”that demonstrate her initiative, curiosity, and early commitment to journalistic integrity. The new structure paints a clear picture of the work she has done and shows readers exactly why her passion is real and hard-earned. Yasmine made excellent progress in just one session, and I believe continuing to refine any college essays with consistent guidance will only make her applications stronger. I recommend meeting once weekly for one hour as needed to support any additional revisions or new essays she may need to complete for her last few applications. If youâ€™d like to discuss Yasmineâ€™s work or next steps, Iâ€™d be happy to schedule a Zoom or phone call at your convenience. Happy Thanksgiving!Â Kristen Luigart, M.Ed., M.A. kristen.luigart@revolutionprep.com +13018205071
A5009: 10918889 | B5009: 45991 | C5009: Kristen Luigart | D5009: Team Plamondon | E5009: 83525 | F5009: Loui Takahashi | G5009: Good Morning Ippei, I'm writing to give you a bit of a wrap up of all the work Loui and I have done in her tutoring sessions so far. Loui's been working extremely hard (especially with all she has going on in school and out), and her ambitious and passionate nature reflects in her writing and intelligence. Together, we have now completed Loui's personal essay, as well as her supplemental essays for Yale, the University of Vermont, Tufts, and -- most recently -- UC Berkeley, which we just finalized with only a little time to spare. Despite the tight timeline, her Berkeley essays turned out excellent. Loui's writing has a strong, innate, sense of storytelling, and a compelling voice to begin with, so working with her on her essays has really been about giving more immediacy and vibrancy to the works. (And sometimes helping her find the motivation to be passionate about some truly awful prompts! ;3) Throughout all the essays, we have focused on strengthening Loui's language and composition to create more compelling narrative flow, express more passion, and illustrate with greater clarity. The key to a good college application essay is being able to use only a couple hundred words to become a fully-fleshed out being to the numbed essay readers at university admissions. With hundreds of thousands of students applying to schools every year, essay readers tend to zone out quickly when essays are repetitive or rote. (I have personal experience with this from being the chair of admissions for UVA's honors dorm, Brown College, which had its own rigorous application essay process.) Therefore, to break through the monotonous repetition of the usual accomplishment lists draped in prose disguised as essays, a student must not only answer their prompts intelligently -- but compellingly, in order to rise above the simple 'fulfilled requirement' stack. I am confident that the essays Loui has brought from this program have all had that spark, and that they use it effectively to highlight how impressive and multifaceted Loui is as an applicant. A good example of this editing process can be seen in how, when we first reviewed Loui's Berkeley drafts, she and I both found them to come across as flat and lacking passion. The prompt, itself, was relatively dry, and without finding a way to feel passionate about the subject, Loui's work came out as simply informative and somewhat distanced. The essays read more like reports than personal reflections. Over several rounds of revision, Loui transformed them all into essays that are far more authentic, vital, and emotionally grounded. For example, the new essay on social mediaâ€™s impact on Loui's life, and her subsequent rejection of it, presents compelling statisticsâ€”such as 5.3 billion selfies are taken per day â€” that highlight Loui's wisdom in learning how to "put down the light-up brick". These striking facts, and the additional comments on the human history of appearance, helped anchor Loui's narrative in something both memorable and meaningful. With Berkeley completed, our next priority is Johns Hopkins. Brainstorming for its essays is Loui's homework for our next session on December 13. After that, we will continue on with her essays for Bowdoin, CMU, and the University of Chicago. To ensure Loui stays comfortably ahead of all deadlines, and maintains her strong momentum, I recommend meeting at least once a week for an hour until all remaining essays are completed. (Ideally, therefore, they will be finished well before their due dates). If youâ€™d like to discuss Louiâ€™s progress or upcoming plans, I would be happy to schedule a Zoom or phone call at your convenience. Warm regards, and Happy Thanksgiving! Kristen Luigart, M.Ed., M.A. Kristen.Luigart@Revolutionprep.com (301)*20-5071
A5010: 10918896 | B5010: 45991 | C5010: Myles Oldroyd | D5010: Team Plamondon | E5010: 90236 | F5010: Brooks Main | G5010: Dear Clayton, Itâ€™s been great working with you and Brooks over the past two months. As we prepare for Brooks's upcoming December SAT, I wanted to share some updates and information about what to expect. I have seen significant improvements in Brooks's two passage reading, measures of central tendency, main ideas, and interpreting equations. They have shown consistent progress in homework and practice tests. This consistent improvement has been evident in a new high score on a practice test of 1440. For this exam, our goal is 1500. While we cannot guarantee a specific score, we have worked diligently towards this goal through B-PRIMES, Title 10, and IESME. It's important to consider the impact of the test zone on Brooks's performance. Ensuring a good night's sleep throughout the week leading up to the test is crucial, as just the night before isn't enough. We have also discussed strategies to manage test anxiety, which can impact scores. I am looking forward to continuing to work with Brooks after the test so that we can work towards further improvements on the SAT. I recommend maintaining at least one session a week until Brooks is happy with his score in order to help them achieve their goals. Please let me know if you have any questions or if there are any adjustments you would like to make to our plan. Iâ€™m also able to schedule a time to talk by phone if that would be helpful. I am happy to support Brooks in their continued academic journey. Thank you and stay safe, Myles O. myles.oldroyd@revolutionprep.com +15304434701
A5011: 10918902 | B5011: 45991 | C5011: Myles Oldroyd | D5011: Team Plamondon | E5011: 83644 | F5011: Reese Migdal | G5011: Dear Kristina, I hope youâ€™re doing well. I wanted to share an update on Reeseâ€™s progress over the past two months and outline our plan moving forward. Over the last two months, Reese has shown meaningful improvement in command of textual evidence, central ideas and details, and trigonometric identities.While working on precalc, Reese seemed to grasp how to view trigonometric identities as a puzzle to solve rather than an annoyance to complete. Our goals over the next phase of instruction include continuing to build his SAT readiness, deepening mastery of reading skills, and ensuring Reese feels confident applying these skills independently. To support this, I recommend regular sessions of at least once a week to prepare for the SAT and keep up with his math course. In the coming sessions, I plan to focus on the reading portion of the SAT including reading comprehension and data analysis, while continuing to reinforce previous learning targets. If you have any questions or if there are adjustments youâ€™d like to make to our plan, please feel free to reach out. Iâ€™m happy to schedule a call if that would be helpful. Thank you for your continued partnership. Itâ€™s a pleasure working with Reese and supporting his academic growth. Thank you and stay safe, Myles O. myles.oldroyd@revolutionprep.com +15304434701
A5012: 10918905 | B5012: 45991 | C5012: Tea Stewart | D5012: Team Haase-Alvey | E5012: 81932 | F5012: Oscar Anguiano | G5012: Hi Oscar, I hope you are having a great fall season. Itâ€™s been wonderful working with you and Oscar over the past couple of months. I wanted to take a moment to share some of the progress weâ€™ve made so far and outline my thoughts moving forward. I have seen significant improvements in Oscarâ€™s understanding and application of graph transformations, particularly with horizontal shifts. Over the semester, he has become much more confident identifying when a function is moving left or right and applying that knowledge accurately in practice problems. In addition, Oscar has shown strong growth in his work with similar triangle ratios. He consistently sets up correct proportions and demonstrates a solid understanding of how corresponding sides relate, which has been a highlight of his progress. His willingness to ask questions and revisit challenging problems has been one of the biggest contributors to this growth, and Iâ€™ve seen his confidence increase as a result. Our current short-term goals for Oscar include strengthening his understanding of function notation, learning to distinguish between stretches and compressions, and accurately identifying reflections across the x- and y-axis. In geometry, short-term goals also include improving his ability to solve proportions that lead to quadratic equations and deepening his understanding of geometric means within triangle relationships. The overall goal remains building Oscarâ€™s confidence and mastery in algebra and geometry so he feels prepared and capable in his math coursework. Based on Oscarâ€™s progress, I suggest we continue with our weekly 60-minute sessions moving forward. Overall, Oscar has worked hard throughout the semester, and his progress and grades reflects that effort. I look forward to continuing to support his growth in these areas. Please feel free to reach out if you have any questions or would like additional updates. Tea S. tea.stewart@revolutionprep.com +17193017642
A5013: 10918906 | B5013: 45991 | C5013: Tea Stewart | D5013: Team Haase-Alvey | E5013: 78245 | F5013: Noor El-Helw | G5013: Hi Dania, I hope you are having a great fall season. Itâ€™s been wonderful working with you and Noor over the past couple of months. I wanted to take a moment to share some of the progress weâ€™ve made so far and outline my thoughts moving forward. I have seen significant improvements in Noorâ€™s understanding and setup of improper integrals. She has consistently demonstrated the ability to recognize when an integral requires limits or a domain adjustment, and her accuracy in forming the correct limit expressions has strengthened throughout the semester. Noor has also done well with tangent line equations for parametric functions, showing confidence in applying derivatives correctly to construct linear approximations. Additionally, she has shown strong mastery in working with speed and velocity vectors of parametric functions, as well as selecting appropriate radian values to construct polar coordinate tables. In integration, Noor has done excellent work eliminating factors to determine unknown constants for partial fractions, a skill that has noticeably improved her efficiency and accuracy. Noor continues to work on several more advanced skills appropriate for Calculus BC. We will focus on strengthening her ability to determine when an improper integral converges or diverges, as well as developing clearer instincts on when extended Lâ€™HÃ´pitalâ€™s Rule is appropriate. She will also benefit from more targeted practice finding vertical and horizontal tangent lines for parametric curves. In polar coordinates, Noorâ€™s next steps include improving her graphing of polar functions with negative r-values and building confidence in interpreting their directional behavior. For integration, she will continue to work on simplifying improper rational expressions before applying partial fractions. We will also devote additional time to solving for t in complex trigonometric equations, an area that will benefit from repeated structured practice. Our current short-term goals for Noor include strengthening her convergence/divergence reasoning, mastering tangent line behavior in parametric curves, and improving clarity with both polar graphing techniques and trigonometric equation solving. The overall goal remains to build Noorâ€™s confidence and mastery across all BC topics so she feels fully prepared for assessments and the AP Exam. Based on Noorâ€™s progress, I recommend maintaining our current schedule of two 60-minute sessions to support steady development as we move into more challenging units. Noor has shown consistent effort throughout the semester, and her progress reflects that dedication. I look forward to continuing to support her growth in these areas. Please feel free to reach out if you have any questions or would like additional updates. Tea S. tea.stewart@revolutionprep.com +17193017642
A5014: 10918907 | B5014: 45991 | C5014: Tea Stewart | D5014: Team Haase-Alvey | E5014: 91642 | F5014: Gavin Gardner | G5014: Hi Shanna, I hope you are having a great fall season. Itâ€™s been wonderful working with you and Gavin over the past couple of months. I wanted to take a moment to share some of the progress weâ€™ve made so far and outline my thoughts moving forward. I have seen improvements in Gavinâ€™s ability to solve systems of equations. He has become more confident setting up equations, choosing appropriate methods, and checking his work for accuracy. Gavin has also done well using the Desmos linear regression formula to analyze linear relationships and interpret results correctly, which has strengthened his problem-solving skills in algebra. In English, he has shown strong progress identifying introductory phrases, demonstrating a clearer understanding of sentence structure and grammatical components. Moving forward, Gavin will continue working on several key areas. In math, he will benefit from becoming more comfortable with the functions and tools embedded within Desmos, which will help him work more efficiently and accurately during assignments. In writing, he will continue developing his ability to combine two complete sentences using the three correct methodsâ€”comma + coordinating conjunction, semicolon, or a period. Improving consistency with these skills will support his clarity and correctness in written communication. Additionally, we will focus on building stronger habits around homework completion, especially avoiding last-minute work so he can focus on quality and comprehension. Our current short-term goals for Gavin include strengthening his command of the three ways to combine complete sentences, improving his use of Desmos tools, and establishing consistent homework routines. The overall goal remains building Gavinâ€™s confidence, accuracy, and independence across his math and writing tasks. Based on Gavinâ€™s progress, I recommend we maintain our current schedule of weekly 60-minute sessions to support steady growth while continuing to reinforce foundational skills. I look forward to continuing to support his growth in these areas. Please feel free to reach out if you have any questions or would like additional updates. Tea S. tea.stewart@revolutionprep.com +17193017642
A5015: 10918908 | B5015: 45991 | C5015: Tea Stewart | D5015: Team Haase-Alvey | E5015: 94355 | F5015: Sanaa Dighe | G5015: Hi Saurabh, I'm excited to reach out to celebrate Sanaaâ€™s amazing progress. Sanaa has worked diligently this semester, and as a result, she scored a 1270 on her PSAT. This is a strong milestone that reflects her effort, consistency, and growth across both math and English skills. I am so proud of the work she has put in and the confidence she is building. Sanaa has shown clear strengths in several areas. In math, she has demonstrated strong familiarity with Desmos functions, has been successful solving for constants of linear functions using Desmos when given points, and has shown solid understanding of special angle relationships involving parallel lines. She has also excelled at setting up equations to determine unknown side lengths and angle measures, as well as setting up proportions for similar shapes. Additionally, she consistently extracts key information from a variety of math problems, which is a major skill for both the SAT and her math coursework. In English, Sanaa has shown strong command of identifying conjunctions, distinguishing between independent and dependent clauses, and applying apostrophe rules accurately. These foundational grammar skills have greatly helped her improve her sentence structure and overall writing clarity. While we are celebrating these successes, there is still targeted work ahead as Sanaa continues preparing for upcoming assessments and the SAT. In math, she will continue improving her approach to multi-condition word problems, strengthening her understanding of similar triangle properties, and finding unknown side lengths. We will also continue reinforcing her understanding of trigonometric relationships so she does not mix up when to use sine, cosine, or tangent. Next session, we will begin working more deeply on triangle trigonometry to extend these skills. In English, Sanaa will continue practicing the three ways to combine two complete sentences, improving her understanding of comma rules, and strengthening her ability to distinguish independent and dependent clauses in more complex sentence structures. She will also benefit from additional practice with transition questions, specifically determining whether clauses are in agreement or disagreement, and from eliminating punctuation-based answer choices more strategically. I am looking forward to continuing to work with Sanaa toward further improvements. I recommend maintaining our current 60 minute weekly sessions so she can continue steady progress toward her next goals, particularly as we begin deeper SAT-level grammar and math strategy work. Sanaa has worked incredibly hard, and her results truly reflect that effort. Iâ€™m excited to keep supporting her as she moves toward her next academic milestones. Please reach out if you have additional questions. Tea S. tea.stewart@revolutionprep.com +17193017642
A5016: 10918913 | B5016: 45991 | C5016: Myles Oldroyd | D5016: Team Plamondon | E5016: 90993 | F5016: Nicolas Dellarocca | G5016: Dear Chris and Kim, Itâ€™s been great working with you and Nico over the past month. As we prepare for Nico's upcoming December SAT, I wanted to share some updates and information about what to expect. I have seen significant improvements in Nico's transitions, measures of central tendency, and word problems. They have shown consistent progress in homework completion, practice tests, and confidence. This consistent improvement has been evident in their continued growth and steady performance across recent practice tests. For this exam, our goal is 1500. While we cannot guarantee a specific score, we have worked diligently towards this goal through IESME, B-PRIMES, and Title 10. It's important to consider the impact of the test zone on Nico's performance. Ensuring a good night's sleep throughout the week leading up to the test is crucial, as just the night before isn't enough. We have also discussed strategies to manage test anxiety, which can impact scores. I am looking forward to hearing how Nico performs on this test. Nico currently has one hour remaining in his account that is unscheduled. Please let me know if you have any questions or if there are any adjustments you would like to make to our plan. Iâ€™m also able to schedule a time to talk by phone if that would be helpful. I am happy to support Nico in their continued academic journey. Thank you and stay safe, Myles O. myles.oldroyd@revolutionprep.com +15304434701
A5017: 10918921 | B5017: 45991 | C5017: Jason Noble | D5017: Team Haase-Alvey | E5017: 94893 | F5017: Abel Uriostegui | G5017: Dear Brittney Uriostegui, I hope you are having a great fall season. Itâ€™s been great working with you and Abel over the past couple of months. I wanted to touch base to share some of the progress weâ€™ve made so far and share my thoughts on the plan moving forward. I have seen significant improvements in Abelâ€™s understanding of decimals, fractions, and foundational algebraic skills. He has shown consistent progress in multiplying and dividing decimals, working with exponents and radicals, solving one-step equations (both standalone and in word problems), and applying operations with positive and negative numbers. This consistent improvement has been evident in his ability to work through increasingly challenging problems, his accuracy with proportional relationships and factors, and his successful transition from proportions into multi-step multiplication, including multiplying within the hundreds. Our current short-term goals for Abel include reinforcing his proportional reasoning, strengthening his fluency with operations involving rational numbers, and continuing to develop his confidence as we introduce more advanced pre-algebra concepts. The overall goal remains keeping him working at an advanced level and preparing him for continued success in higher-level math. Based on Abelâ€™s progress, I recommend continuing to meet for one hour each weekâ€”either as two 30-minute sessions on Monday and Wednesday or as a single one-hour session. This schedule supports steady, accelerated growth and gives Abel consistent practice as he advances into more rigorous material. If you'd like to continue working together on achieving these goals, you can easily use this link to add the hours to your account today: https://my.revolutionprep.com/s/7cHIgWpgJo. Please let me know if you have any questions or if there are any adjustments you would like to make to our plan. Iâ€™m happy to schedule a time to talk by phone if that would be helpful. I look forward to supporting Abel in his continued academic journey. Best regards, Jason N. jason.noble@revolutionprep.com +12162627470
A5018: 10918923 | B5018: 45991 | C5018: Jason Noble | D5018: Team Haase-Alvey | E5018: 88830 | F5018: Noah Antonio Magana | G5018: Dear Tricia Marie Nepomuceno, I hope you are having a great fall season. Itâ€™s been great working with you and Noah over the past couple of months. I wanted to touch base to share some of the progress weâ€™ve made so far and share my thoughts on the plan moving forward. I have seen significant improvements in Noahâ€™s punctuation, grammar, and ability to complete and edit his school assignments. He has shown consistent progress in working through his homework, reviewing grammar concepts, practicing journaling, and building his confidence with both reading and writing tasks. This consistent improvement has been evident in his increased independence with school assignments, his completion of editing practice, and his engagement in introductory Python coding lessons. Our current short-term goals for Noah include continuing to complete school assignments on time, strengthening his reading comprehension through summary writing, and further developing his narrative and academic writing clarity. The overall goal remains improving his confidence and skills in writing, reading comprehension, andâ€”if he choosesâ€”his progression through Python coding units. Based on Noahâ€™s progress, I recommend continuing to meet once a week for one hour to focus on his school assignments or, when he has no homework, to practice reading passages and summarizing them to further improve his writing skills. If he would like to continue learning Python, we can meet once a week for that as well, though those sessions should remain separate to keep each focus area structured and effective. If you'd like to continue working together on achieving these goals, you can redeem more credits through your Bright Horizon's portal. After you redeem your credits, you will receive an email from Revolution Prep to add the hours to your account. Please let me know if you have any questions or if there are any adjustments you would like to make to our plan. Iâ€™m happy to schedule a time to talk by phone if that would be helpful. I look forward to supporting Noah in his continued academic journey. Best regards, Jason N. jason.noble@revolutionprep.com +12162627470
... A6299: 10936306 | B6299: 46018 | C6299: River Nunez | D6299: Team De Groot | E6299: 91622 | F6299: Sloan Gardner | G6299: Dear Shanna, I hope you are having a great holiday season. Itâ€™s been great working with you and Sloan over the past couple of months. I wanted to touch base to share some of the progress weâ€™ve made so far and share my thoughts on the plan moving forward. Sloanâ€™s first practice exam showed a need to review Math concepts and that has been our main focus. Weâ€™ve reviewed how to use MAPS strategy, the different Forms of Quadratics, constants problems, and how to use the Desmos calculator. Sloan has noted how helpful and efficient the Desmos calculator can be for solving equations and has been quick to apply these skills to practice problems. Every time we work together, Sloan is quicker to work through problems, better at remembering strategies to use, and answers correctly more often than not. Iâ€™ve been especially impressed with how quickly he is able to learn strategies and apply them correctly almost immediately. Constants are usually hard for students, but Sloan understood and applied matching strategy with ease. Iâ€™m extremely pleased with his progress and look forward to seeing how this translates to his score reports. Our current short-term goals for Sloan are to improve his math skills and ability to apply MAPS strategy in order to breakdown problems. The overall goal remains general score improvement and confidence in test taking. Based on Sloan's progress, I recommend we continue meeting for one 60-minute session per week in order to prepare for his next official exam. As we move closer to March, I will be increasing the frequency of his practice exams in order to help his prepare. It looks like Sloan has a fair amount of hours left in his account, but not enough to stay on track. You can use the link below to add more hours to your account. Please let me know if you have any questions or if there are any adjustments you would like to make to our plan. Iâ€™m happy to schedule a time to talk by phone if that would be helpful. I look forward to supporting Sloan in his continued academic journey. Best, River N. river.nunez@revolutionprep.com +14088020170

Sheet MonthlyMetricFullData
A1: 11-30/25-12-27-25
G2: 0.8 | J2: 1 | K2: 0.1 | L2: 0.9 | M2: 0.95 | O2: 0.8
A3: Bottom Range Lower Than | G3: 0.7 | J3: 0.8 | K3: 0.2 | L3: 0.75 | M3: 0.8 | O3: 0.5
A4: Tutor Name | B4: Current Tier | C4: Faculty Leader Name | D4: Hire Date | E4: Delivery Target | F4: Avg. Delivery Actual | G4: % to Delivery Target | H4: Availability Target | I4: Avg. Availability Actual | J4: % to Availability Target | K4: Prep Time % | L4: % Parents Updates Done on Time | M4: % Sessions on Time | N4: Ratio of PPW Events with Attached PPWs | O4: % of Active Students with Progress Updates Completed | P4: # of NPS Scores | Q4: Avg. NPS Score | R4: Weighted Repurchases | S4: Autoattendance | T4: New 1 on 1 Students | U4: total 1 on 1 students | V4: Average AI Score for Progress Updates
A5: Akeema Williams | B5: Advanced | C5: Ian Plamondon | D5: 45519 | E5: 30 | F5: 29.38 | G5: 0.9792 | H5: 38 | I5: 37.13 | J5: 0.977 | K5: 0.2842 | L5: 0.94736842 | M5: 1 | N5: 0/0 | O5: 0.9047619 | P5: 1 | Q5: 10 | R5: 19 | T5: 9 | U5: 44 | V5: 3.9583333
A6: Alex Small | B6: Premium | C6: Ela Cross | D6: 43907 | E6: 12 | F6: 4.25 | G6: 0.3542 | H6: 16 | I6: 22.38 | J6: 1.3984 | K6: 0.4166 | L6: 0.90909091 | M6: 1 | N6: 0/0 | O6: 0.66666667 | T6: 0 | U6: 7
A7: Alexa Pinera | B7: Premium | C7: Ian Plamondon | D7: 43812 | E7: 30 | F7: 17.9 | G7: 0.5965 | H7: 38 | I7: 69.06 | J7: 1.8174 | K7: 0.0591 | L7: 0.97560976 | M7: 1 | N7: 1/1 | O7: 0.8125 | P7: 1 | Q7: 10 | R7: 4 | T7: 2 | U7: 18 | V7: 3.4444444
A8: Alexandra Berrios | B8: Advanced | C8: Kristin Haase-Alvey | D8: 45755 | E8: 12 | F8: 13.13 | G8: 1.0938 | H8: 16 | I8: 14.81 | J8: 0.9258 | K8: 0.25 | L8: 0.51428571 | M8: 0.94736842 | N8: 1/1 | O8: 0.64705882 | R8: 3 | S8: 9 | T8: 3 | U8: 25 | V8: 4
A9: Alexis Boucher | B9: Distinguished | C9: Ian Plamondon | D9: 43749 | E9: 30 | F9: 10.88 | G9: 0.3625 | H9: 38 | I9: 35.75 | J9: 0.9408 | K9: 0.1234 | L9: 0.93548387 | M9: 0.97435897 | N9: 0/0 | O9: 1 | R9: 1 | T9: 1 | U9: 17 | V9: 2.6666667
A10: Alison Trumbull | B10: Premium | C10: Geoff St. Marie | D10: 39309 | E10: 12 | F10: 4.44 | G10: 0.3698 | H10: 16 | I10: 18.69 | J10: 1.168 | K10: 0.0858 | L10: 0.7 | M10: 0.84615385 | N10: 1/1 | O10: 1 | R10: 6 | T10: 1 | U10: 7 | V10: 5
A11: Allison Peck | B11: Distinguished | C11: Kristin Haase-Alvey | D11: 45223 | E11: 12 | F11: 5.5 | G11: 0.4583 | H11: 16 | I11: 16.06 | J11: 1.0039 | K11: 0.4843 | L11: 1 | M11: 0.94117647 | N11: 0/0 | O11: 1 | P11: 1 | Q11: 10 | R11: 1 | T11: 0 | U11: 4 | V11: 4.6666667
A12: Amber Maldonado | B12: Advanced | C12: Annelies de Groot | D12: 45683 | E12: 30 | F12: 0 | G12: 0 | H12: 38 | I12: 2 | J12: 0.0526 | N12: 0/0 | O12: 1 | T12: 0 | U12: 0
A13: Amelia Sain | B13: Premium | C13: Jessica Milner | D13: 43479 | E13: 30 | F13: 7.88 | G13: 0.2625 | H13: 38 | I13: 33.25 | J13: 0.875 | K13: 0.1375 | L13: 0.94444444 | M13: 1 | N13: 0/0 | O13: 0.7 | R13: 2 | T13: 0 | U13: 9 | V13: 4.5
A14: Amy Kim | B14: Advanced | C14: Katherine Marino | D14: 46020 | E14: 30 | H14: 38 | N14: 0/0 | T14: 0 | U14: 0
A15: Ana Heiser | B15: Distinguished | C15: Kristin Haase-Alvey | D15: 45538 | E15: 30 | F15: 9.5 | G15: 0.3167 | H15: 38 | I15: 32.63 | J15: 0.8586 | K15: 0.1032 | L15: 0.69565217 | M15: 0.97222222 | N15: 1/1 | O15: 1 | S15: 1 | T15: 4 | U15: 12 | V15: 3
A16: Andres Jarquin | B16: Advanced | C16: Ian Plamondon | D16: 45876 | E16: 30 | F16: 23.38 | G16: 0.7792 | H16: 38 | I16: 32.06 | J16: 0.8438 | K16: 0.1524 | L16: 1 | M16: 0.97247706 | N16: 0/0 | O16: 0.18181818 | R16: 8 | T16: 2 | U16: 26 | V16: 5
A17: Andrew Brown | B17: Distinguished | C17: Ian Plamondon | D17: 44218 | E17: 30 | F17: 22.25 | G17: 0.7417 | H17: 38 | I17: 48.06 | J17: 1.2648 | K17: 0.1206 | L17: 0.8 | M17: 0.95 | N17: 0/0 | O17: 0.76190476 | R17: 6 | T17: 6 | U17: 27 | V17: 2.8888889
A18: Andrew Gehlot | B18: Premium | C18: Jessica Milner | D18: 42825 | E18: 30 | F18: 14.38 | G18: 0.4792 | H18: 38 | I18: 38.13 | J18: 1.0033 | K18: 0.1855 | L18: 0.94117647 | M18: 1 | N18: 0/0 | O18: 0.8 | R18: 1 | S18: 9 | T18: 0 | U18: 15
A19: Anna Gilbert | B19: Distinguished | C19: Kristin Haase-Alvey | D19: 45294 | E19: 12 | F19: 4.25 | G19: 0.3542 | H19: 16 | I19: 14 | J19: 0.875 | L19: 1 | M19: 1 | N19: 0/0 | O19: 1 | R19: 3 | T19: 0 | U19: 6 | V19: 4
A20: Armand Brouty | B20: Distinguished | C20: Ian Plamondon | D20: 44015 | E20: 30 | F20: 19 | G20: 0.6333 | H20: 38 | I20: 58.5 | J20: 1.5395 | K20: 0.2028 | L20: 1 | M20: 1 | N20: 6/7 | O20: 0.94444444 | R20: 0 | T20: 6 | U20: 21 | V20: 4.6666667
A21: Aryan Jazayeri | B21: Premium | C21: Kristin Haase-Alvey | D21: 44260 | E21: 20 | F21: 7.75 | G21: 0.3875 | H21: 24 | I21: 21.75 | J21: 0.9063 | K21: 0.1481 | L21: 1 | M21: 1 | N21: 1/1 | O21: 0.81818182 | R21: 2 | T21: 1 | U21: 12 | V21: 3.2
A22: Ashley Scorsone | B22: Premium | C22: Geoff St. Marie | D22: 42909 | E22: 35 | F22: 26.88 | G22: 0.7679 | H22: 43 | I22: 52.31 | J22: 1.2166 | K22: 0.1375 | L22: 0.85454545 | M22: 0.91463415 | N22: 1/1 | O22: 0.96428571 | P22: 1 | Q22: 10 | S22: 2 | T22: 2 | U22: 24 | V22: 2.1
A23: Autumn Reed | B23: Advanced | C23: Nikki Pencak | D23: 46003 | E23: 20 | F23: 0 | G23: 0 | H23: 24 | I23: 14 | J23: 0.5833 | N23: 0/0 | T23: 0 | U23: 0
A24: Ayman Smoot | B24: Advanced | C24: Annelies de Groot | D24: 45225 | E24: 12 | F24: 12.88 | G24: 1.0729 | H24: 16 | I24: 24.63 | J24: 1.5391 | K24: 0.3062 | L24: 1 | M24: 0.84 | N24: 3/4 | O24: 0.66666667 | R24: 8 | T24: 3 | U24: 16 | V24: 3
A25: Ben Chamberlain | B25: Advanced | C25: Kristin Haase-Alvey | D25: 45967 | E25: 35 | F25: 29.13 | G25: 0.8321 | H25: 43 | I25: 43.88 | J25: 1.0203 | K25: 0.3222 | L25: 0.85897436 | M25: 0.99090909 | N25: 3/17 | O25: 0.85714286 | P25: 1 | Q25: 8 | R25: 7 | T25: 31 | U25: 40 | V25: 3.4615385
A26: Ben Taylor | B26: Premium | C26: Jessica Milner | D26: 44281 | E26: 30 | F26: 7.38 | G26: 0.2458 | H26: 38 | I26: 40.33 | J26: 1.0614 | K26: 0.2058 | L26: 1 | M26: 1 | N26: 1/1 | O26: 1 | R26: 2 | T26: 1 | U26: 12 | V26: 3.6
A27: Brandon Engle | B27: Advanced | C27: Annelies de Groot | D27: 45853 | E27: 35 | F27: 26.25 | G27: 0.75 | H27: 43 | I27: 39.19 | J27: 0.9113 | K27: 0.3342 | L27: 0.98591549 | M27: 1 | N27: 8/9 | O27: 0.8 | P27: 1 | Q27: 10 | R27: 22 | T27: 27 | U27: 48 | V27: 4.2857143
A28: Brandon Lora | B28: Advanced | C28: Annelies de Groot | D28: 45944 | E28: 30 | F28: 9.25 | G28: 0.3083 | H28: 38 | I28: 19.75 | J28: 0.5197 | K28: 0.1911 | L28: 1 | M28: 1 | N28: 1/1 | O28: 0.4 | R28: 2 | T28: 1 | U28: 19 | V28: 4.5
A29: Brenna Hubnik | B29: Advanced | C29: Annelies de Groot | D29: 45194 | E29: 12 | F29: 12 | G29: 1 | H29: 16 | I29: 18.25 | J29: 1.1406 | K29: 0.2643 | L29: 1 | M29: 1 | N29: 0/0 | O29: 0.82352941 | R29: 6 | T29: 0 | U29: 17 | V29: 3.8333333
A30: Brian Cohen | B30: Premium | C30: Jessica Milner | D30: 43536 | E30: 12 | F30: 6.25 | G30: 0.5208 | H30: 16 | I30: 18.25 | J30: 1.1406 | K30: 0.2424 | L30: 1 | M30: 1 | N30: 2/2 | O30: 1 | P30: 1 | Q30: 10 | T30: 3 | U30: 10 | V30: 3
A31: Brian James | B31: Advanced | C31: Annelies de Groot | D31: 45264 | E31: 30 | F31: 26.5 | G31: 0.8833 | H31: 38 | I31: 37.5 | J31: 0.9868 | K31: 0.1521 | L31: 1 | M31: 1 | N31: 0/2 | O31: 0.90909091 | R31: 10 | S31: 9 | T31: 13 | U31: 41 | V31: 2.6190476
A32: Brock Dilley | B32: Advanced | C32: Nikki Pencak | D32: 45992 | E32: 35 | F32: 12 | G32: 0.3429 | H32: 43 | I32: 39.38 | J32: 0.9157 | K32: 0.1646 | L32: 0.83333333 | M32: 0.95348837 | N32: 10/12 | O32: 0 | P32: 1 | Q32: 10 | R32: 2 | T32: 18 | U32: 18
A33: Bryant Salinas | B33: Premium | C33: Jessica Milner | D33: 43363 | E33: 30 | F33: 19.67 | G33: 0.6556 | H33: 38 | I33: 34.56 | J33: 0.9095 | K33: 0.0882 | L33: 0.76190476 | M33: 0.93333333 | N33: 1/2 | O33: 0.6875 | R33: 4 | S33: 21 | T33: 5 | U33: 19 | V33: 2
A34: Cait White | B34: Premium | C34: Ela Cross | D34: 43903 | E34: 12 | F34: 2.25 | G34: 0.1875 | H34: 16 | I34: 15.81 | J34: 0.9883 | L34: 1 | M34: 1 | N34: 0/0 | O34: 1 | S34: 1 | T34: 0 | U34: 3
A35: Cameron Hojecki | B35: Advanced | C35: Geoff St. Marie | D35: 45958 | E35: 20 | F35: 13.5 | G35: 0.675 | H35: 24 | I35: 25.56 | J35: 1.0651 | K35: 0.4309 | L35: 0.97297297 | M35: 1 | N35: 3/3 | O35: 1 | P35: 1 | Q35: 10 | R35: 7 | T35: 5 | U35: 19 | V35: 4.7777778
A36: Camryn To | B36: Distinguished | C36: Kristin Haase-Alvey | D36: 45261 | E36: 12 | F36: 7.25 | G36: 0.6042 | H36: 16 | I36: 19.56 | J36: 1.2227 | K36: 0.0603 | L36: 0.93333333 | M36: 1 | N36: 0/0 | O36: 0.875 | R36: 3 | T36: 0 | U36: 10 | V36: 5
A37: Cara Rabaev (McLaughlin) | B37: Distinguished | C37: Ian Plamondon | D37: 45197 | E37: 30 | F37: 27.63 | G37: 0.9208 | H37: 38 | I37: 34.69 | J37: 0.9128 | K37: 0.2594 | L37: 0.98529412 | M37: 0.93457944 | N37: 2/3 | O37: 0.66666667 | S37: 2 | T37: 5 | U37: 33 | V37: 5
A38: Carina Shanahan | B38: Advanced | C38: Kristin Haase-Alvey | D38: 45757 | E38: 30 | F38: 28.5 | G38: 0.95 | H38: 38 | I38: 35.25 | J38: 0.9276 | K38: 0.1067 | L38: 0.83783784 | M38: 0.9826087 | N38: 2/4 | O38: 0.7826087 | R38: 13 | S38: 0 | T38: 12 | U38: 37 | V38: 4.1111111
A39: Casey Young | B39: Advanced | C39: Ela Cross | D39: 45786 | E39: 35 | F39: 32.5 | G39: 0.9286 | H39: 43 | I39: 43.63 | J39: 1.0145 | K39: 0.1454 | L39: 0.99047619 | M39: 0.99418605 | N39: 10/11 | O39: 0.96 | R39: 22 | T39: 19 | U39: 57 | V39: 3.5555556
A40: Charlie Anderson | B40: Advanced | C40: Annelies de Groot | D40: 45684 | E40: 30 | F40: 27.38 | G40: 0.9125 | H40: 38 | I40: 35.56 | J40: 0.9359 | K40: 0.0917 | L40: 1 | M40: 1 | N40: 4/4 | O40: 0.82758621 | R40: 4 | T40: 8 | U40: 36
A41: Chazlee Myers | B41: Advanced | C41: Ian Plamondon | D41: 45666 | E41: 30 | F41: 16.38 | G41: 0.5458 | H41: 38 | I41: 30 | J41: 0.7895 | K41: 0.3304 | L41: 0.54347826 | M41: 0.92647059 | N41: 1/11 | O41: 0.78571429 | P41: 1 | Q41: 10 | R41: 10 | T41: 17 | U41: 34
A42: Cheyanne Jones | B42: Advanced | C42: Nikki Pencak | D42: 45999 | E42: 30 | F42: 3 | G42: 0.1 | H42: 38 | I42: 35.17 | J42: 0.9254 | K42: 0.3425 | L42: 1 | M42: 1 | N42: 4/5 | T42: 8 | U42: 8
A43: Chris Prouty | B43: Premium | C43: Annelies de Groot | D43: 43903 | E43: 20 | F43: 9.88 | G43: 0.4938 | H43: 24 | I43: 28.69 | J43: 1.1953 | K43: 0.3478 | L43: 0.96 | M43: 0.94117647 | N43: 0/0 | O43: 1 | T43: 1 | U43: 12 | V43: 3.2
A44: Christelle Rocha | B44: Advanced | C44: Katherine Marino | D44: 45978 | E44: 35 | F44: 5.75 | G44: 0.1643 | H44: 43 | I44: 38.31 | J44: 0.891 | K44: 1.05 | L44: 1 | M44: 1 | N44: 5/6 | S44: 0 | T44: 12 | U44: 12
A45: Christian Collins | B45: Premium | C45: Jessica Milner | D45: 43479 | E45: 30 | F45: 19.23 | G45: 0.641 | H45: 38 | I45: 52.67 | J45: 1.386 | K45: 0.0788 | L45: 1 | M45: 1 | N45: 1/1 | O45: 0.88 | P45: 1 | Q45: 10 | R45: 2 | T45: 1 | U45: 24 | V45: 2.8
A46: Christian Steiner | B46: Advanced | C46: Kristin Haase-Alvey | D46: 45282 | E46: 30 | F46: 26.5 | G46: 0.8833 | H46: 38 | I46: 37 | J46: 0.9737 | K46: 0.2271 | L46: 0.97142857 | M46: 0.93203883 | N46: 0/1 | O46: 0.76666667 | R46: 11 | T46: 3 | U46: 36 | V46: 3.4
A47: Christina Hayes | B47: Premium | C47: Jessica Milner | D47: 42576 | E47: 30 | F47: 10.38 | G47: 0.3458 | H47: 38 | I47: 36.13 | J47: 0.9507 | K47: 0.0506 | L47: 0.8 | M47: 0.97619048 | N47: 1/2 | O47: 0.64285714 | T47: 3 | U47: 12 | V47: 1.8333333
A48: Christine Santos | B48: Premium | C48: Ela Cross | D48: 43441 | E48: 12 | F48: 9.25 | G48: 0.7708 | H48: 16 | I48: 20.63 | J48: 1.2891 | K48: 0.4181 | L48: 0.63157895 | M48: 0.74285714 | N48: 0/0 | O48: 0.44444444 | R48: 3 | S48: 26 | T48: 1 | U48: 11 | V48: 3
A49: Clark Howard | B49: Advanced | C49: Ela Cross | D49: 45289 | E49: 30 | F49: 27.31 | G49: 0.9104 | H49: 38 | I49: 36.75 | J49: 0.9671 | K49: 0.185 | L49: 0.79545455 | M49: 0.99212598 | N49: 6/7 | O49: 0.73076923 | P49: 1 | Q49: 10 | R49: 11 | T49: 14 | U49: 47 | V49: 4
A50: Colin Cody | B50: Advanced | C50: Ela Cross | D50: 45750 | E50: 30 | F50: 26.75 | G50: 0.8917 | H50: 38 | I50: 37.06 | J50: 0.9753 | K50: 0.2751 | L50: 0.98765432 | M50: 0.96747967 | N50: 1/4 | O50: 0.91666667 | R50: 8 | T50: 11 | U50: 40 | V50: 3.6
A51: Cristina Ascenzi Pettenuzzo | B51: Advanced | C51: Ian Plamondon | D51: 45702 | E51: 30 | F51: 28.5 | G51: 0.95 | H51: 38 | I51: 41.5 | J51: 1.0921 | K51: 0.2832 | L51: 0.97530864 | M51: 0.9826087 | N51: 5/8 | O51: 1 | P51: 1 | Q51: 10 | R51: 13 | T51: 15 | U51: 48 | V51: 2.875
A52: Daniel Esquivel-Reynoso | B52: Advanced | C52: Annelies de Groot | D52: 45756 | E52: 20 | F52: 21 | G52: 1.05 | H52: 24 | I52: 26.94 | J52: 1.1224 | K52: 0.2777 | L52: 0.96153846 | M52: 1 | N52: 1/4 | O52: 0.55 | P52: 1 | Q52: 10 | R52: 7 | T52: 11 | U52: 29 | V52: 3
A53: Daniel Olson | B53: Advanced | C53: Annelies de Groot | D53: 45875 | E53: 30 | F53: 30.63 | G53: 1.0208 | H53: 38 | I53: 36.94 | J53: 0.972 | K53: 0.2508 | L53: 0.88888889 | M53: 1 | N53: 1/8 | O53: 0.24 | P53: 1 | Q53: 10 | R53: 7 | T53: 11 | U53: 42 | V53: 3.8333333
A54: Daniel Severance | B54: Premium | C54: Jessica Milner | D54: 43322 | E54: 35 | F54: 21.25 | G54: 0.6071 | H54: 43 | I54: 53.25 | J54: 1.2384 | K54: 0.0652 | L54: 1 | M54: 1 | N54: 2/6 | O54: 0.73684211 | R54: 5 | T54: 5 | U54: 18 | V54: 4
A55: David Alcantara | B55: Distinguished | C55: Ela Cross | D55: 45191 | E55: 30 | F55: 15.5 | G55: 0.5167 | H55: 38 | I55: 37.75 | J55: 0.9934 | K55: 0.0598 | L55: 1 | M55: 1 | N55: 1/2 | O55: 0.5 | R55: 2 | T55: 5 | U55: 19 | V55: 4
A56: David Keder | B56: Advanced | C56: Kristin Haase-Alvey | D56: 45212 | E56: 12 | F56: 14 | G56: 1.1667 | H56: 16 | I56: 22 | J56: 1.375 | K56: 0.1047 | L56: 0.65517241 | M56: 0.88636364 | N56: 0/0 | O56: 0.58333333 | R56: 3 | S56: 17 | T56: 5 | U56: 18 | V56: 3.1666667
A57: Dehavion Knight | B57: Advanced | C57: Ela Cross | D57: 45196 | E57: 12 | F57: 13.5 | G57: 1.125 | H57: 16 | I57: 21.19 | J57: 1.3242 | K57: 0.3065 | L57: 1 | M57: 0.95 | N57: 0/3 | O57: 0.66666667 | R57: 8 | T57: 5 | U57: 16
A58: Delphine Hintz | B58: Advanced | C58: Geoff St. Marie | D58: 45947 | E58: 12 | F58: 12.63 | G58: 1.0521 | H58: 16 | I58: 19.44 | J58: 1.2148 | K58: 0.3437 | L58: 1 | M58: 1 | N58: 0/0 | O58: 1 | R58: 13 | T58: 3 | U58: 15 | V58: 3.9
A59: Derek Fox | B59: Advanced | C59: Katherine Marino | D59: 45999 | E59: 12 | F59: 0 | G59: 0 | H59: 16 | I59: 14.5 | J59: 0.9063 | N59: 0/0 | T59: 0 | U59: 0
A60: Diamond Anderson | B60: Advanced | C60: Kristin Haase-Alvey | D60: 44015 | E60: 12 | F60: 5.63 | G60: 0.4688 | H60: 16 | I60: 11.17 | J60: 0.6979 | K60: 0.2719 | L60: 1 | M60: 1 | N60: 0/0 | O60: 0.90909091 | R60: 6 | T60: 2 | U60: 11 | V60: 3.6666667
A61: Diana Hoyer | B61: Distinguished | C61: Ian Plamondon | D61: 44281 | E61: 35 | F61: 13.63 | G61: 0.3893 | H61: 43 | I61: 29.63 | J61: 0.689 | K61: 0.2145 | L61: 1 | M61: 1 | N61: 0/0 | O61: 0.95 | R61: 3 | T61: 1 | U61: 18 | V61: 3.6666667
A62: Dorothy McDaniel | B62: Premium | C62: Ian Plamondon | D62: 44613 | E62: 30 | F62: 1.5 | G62: 0.05 | H62: 38 | I62: 25.38 | J62: 0.6678 | L62: 0.6 | M62: 1 | N62: 1/1 | O62: 0 | R62: 2 | T62: 1 | U62: 3
A63: Eddie Cayia | B63: Advanced | C63: Annelies de Groot | D63: 45717 | E63: 35 | F63: 27.88 | G63: 0.7964 | H63: 43 | I63: 34.44 | J63: 0.8009 | K63: 0.3401 | L63: 0.90540541 | M63: 0.96747967 | N63: 2/14 | O63: 0.77272727 | R63: 11 | T63: 24 | U63: 52 | V63: 2
A64: Eddie Rodriguez | B64: Distinguished | C64: Ian Plamondon | D64: 45206 | E64: 30 | F64: 15.88 | G64: 0.5292 | H64: 38 | I64: 40.94 | J64: 1.0773 | K64: 0.1878 | L64: 0.97619048 | M64: 1 | N64: 0/2 | O64: 0.52631579 | P64: 2 | Q64: 10 | S64: 0 | T64: 5 | U64: 21 | V64: 4.6666667
A65: Eden Rasmussen | B65: Advanced | C65: Ian Plamondon | D65: 44330 | E65: 30 | F65: 17.88 | G65: 0.5958 | H65: 38 | I65: 36.58 | J65: 0.9627 | K65: 0.2235 | L65: 1 | M65: 0.94666667 | N65: 0/4 | O65: 0.73913043 | P65: 2 | Q65: 10 | R65: 10 | T65: 9 | U65: 27
A66: Edwin West | B66: Advanced | C66: Ela Cross | D66: 45264 | E66: 12 | F66: 11.5 | G66: 0.9583 | H66: 16 | I66: 16 | J66: 1 | K66: 0.1645 | L66: 0.96666667 | M66: 0.98039216 | N66: 5/5 | O66: 0.92307692 | P66: 1 | Q66: 10 | R66: 4 | T66: 5 | U66: 20 | V66: 2.7777778
A67: Elain Ng | B67: Distinguished | C67: Ela Cross | D67: 45516 | E67: 20 | F67: 18.63 | G67: 0.9313 | H67: 24 | I67: 42.75 | J67: 1.7813 | K67: 0.0945 | L67: 1 | M67: 1 | N67: 1/1 | O67: 0.68181818 | R67: 3 | T67: 1 | U67: 25 | V67: 3
A68: Elijah Ramirez | B68: Premium | C68: Ian Plamondon | D68: 44240 | E68: 30 | F68: 14 | G68: 0.4667 | H68: 38 | I68: 36.81 | J68: 0.9688 | K68: 0.18 | L68: 0.96153846 | M68: 1 | N68: 0/0 | O68: 1 | T68: 0 | U68: 14 | V68: 3
A69: Elizabeth Simons | B69: Advanced | C69: Kristin Haase-Alvey | D69: 45741 | E69: 12 | F69: 13.63 | G69: 1.1354 | H69: 16 | I69: 14.88 | J69: 0.9297 | K69: 0.1792 | L69: 1 | M69: 1 | N69: 1/3 | O69: 0.58333333 | R69: 6 | T69: 4 | U69: 19
A70: Elliot Emadian | B70: Advanced | C70: Annelies de Groot | D70: 45859 | E70: 30 | F70: 30.5 | G70: 1.0167 | H70: 38 | I70: 39.19 | J70: 1.0313 | K70: 0.0895 | L70: 0.98809524 | M70: 1 | N70: 5/8 | O70: 0.875 | R70: 8 | T70: 32 | U70: 56 | V70: 3.6666667
A71: Ellyn Schinke | B71: Premium | C71: Annelies de Groot | D71: 43535 | E71: 12 | F71: 9.13 | G71: 0.7604 | H71: 16 | I71: 15.19 | J71: 0.9492 | K71: 0.2049 | L71: 0.91666667 | M71: 0.93333333 | N71: 0/0 | O71: 0.41666667 | T71: 0 | U71: 11
A72: Emma Brugman | B72: Advanced | C72: Kristin Haase-Alvey | D72: 45838 | E72: 35 | F72: 27.75 | G72: 0.7929 | H72: 43 | I72: 45.17 | J72: 1.0504 | K72: 0.165 | L72: 1 | M72: 0.984 | N72: 3/7 | O72: 0.84 | R72: 14 | S72: 4 | T72: 15 | U72: 46 | V72: 3.173913
A73: Eric Chang | B73: Advanced | C73: Annelies de Groot | D73: 45768 | E73: 30 | F73: 26.13 | G73: 0.8708 | H73: 38 | I73: 31 | J73: 0.8158 | K73: 0.1481 | L73: 0.97183099 | M73: 0.97169811 | N73: 1/1 | O73: 0.44 | P73: 1 | Q73: 10 | R73: 19 | T73: 8 | U73: 38 | V73: 3.2857143
A74: Erica Ichikawa | B74: Distinguished | C74: Ela Cross | D74: 45225 | E74: 12 | F74: 5.88 | G74: 0.4896 | H74: 16 | I74: 16.19 | J74: 1.0117 | K74: 0.3245 | L74: 0.93333333 | M74: 1 | N74: 0/0 | O74: 0.8 | P74: 1 | Q74: 10 | R74: 6 | S74: 2 | T74: 0 | U74: 10
A75: Ernie Chu | B75: Advanced | C75: Geoff St. Marie | D75: 45695 | E75: 30 | F75: 38.5 | G75: 1.2833 | H75: 38 | I75: 43.56 | J75: 1.1464 | K75: 0.0991 | L75: 0.98095238 | M75: 0.99378882 | N75: 5/10 | O75: 0.65625 | R75: 18 | T75: 25 | U75: 61 | V75: 3.3333333
A76: Faith Rogers | B76: Distinguished | C76: Ian Plamondon | D76: 44330 | E76: 30 | F76: 10.75 | G76: 0.3583 | H76: 38 | I76: 26.08 | J76: 0.6864 | K76: 0.141 | L76: 1 | M76: 0.84615385 | N76: 0/1 | O76: 1 | R76: 2 | T76: 1 | U76: 16 | V76: 3
A77: Gabriel Saint Cyr | B77: Distinguished | C77: Geoff St. Marie | D77: 43685 | E77: 12 | F77: 5.75 | G77: 0.4792 | H77: 16 | I77: 15.88 | J77: 0.9922 | K77: 0.2499 | L77: 1 | M77: 1 | N77: 0/0 | O77: 0.88888889 | R77: 1 | T77: 0 | U77: 11 | V77: 3.6666667
A78: Gale Hermes | B78: Premium | C78: Ian Plamondon | D78: 44246 | E78: 30 | F78: 16 | G78: 0.5333 | H78: 38 | I78: 36.5 | J78: 0.9605 | K78: 0.1594 | L78: 0.89189189 | M78: 0.96774194 | N78: 0/1 | O78: 0.85714286 | P78: 1 | Q78: 8 | R78: 3 | S78: 5 | T78: 2 | U78: 19 | V78: 4
A79: Gigi Glover | B79: Distinguished | C79: Ian Plamondon | D79: 43903 | E79: 30 | F79: 15.13 | G79: 0.5042 | H79: 38 | I79: 40.56 | J79: 1.0674 | K79: 0.1495 | L79: 0.97058824 | M79: 0.96428571 | N79: 0/1 | O79: 0.84615385 | R79: 2 | T79: 2 | U79: 11 | V79: 3
A80: Gillian Ware | B80: Advanced | C80: Kristin Haase-Alvey | D80: 45747 | E80: 20 | F80: 10.63 | G80: 0.5313 | H80: 24 | I80: 17.31 | J80: 0.7214 | K80: 0.0625 | L80: 0.72222222 | M80: 1 | N80: 1/2 | O80: 0.76190476 | P80: 2 | Q80: 8.5 | R80: 3 | S80: 6 | T80: 1 | U80: 21 | V80: 3.2
A81: Hannah Duliere | B81: Premium | C81: Jessica Milner | D81: 44218 | E81: 30 | F81: 20.75 | G81: 0.6917 | H81: 38 | I81: 58.38 | J81: 1.5362 | K81: 0.2097 | L81: 0.95121951 | M81: 1 | N81: 0/1 | O81: 0.92 | P81: 1 | Q81: 10 | R81: 3 | T81: 2 | U81: 25 | V81: 3.4285714
A82: Hannah Ervitz | B82: Advanced | C82: Kristin Haase-Alvey | D82: 45670 | E82: 30 | F82: 22 | G82: 0.7333 | H82: 38 | I82: 29.56 | J82: 0.778 | K82: 0.1923 | L82: 0.97014925 | M82: 1 | N82: 1/5 | O82: 1 | P82: 1 | Q82: 10 | R82: 7 | S82: 1 | T82: 11 | U82: 39 | V82: 1.0833333
A83: Hannah Lodge | B83: Premium | C83: Ian Plamondon | D83: 43922 | E83: 30 | F83: 17.63 | G83: 0.5875 | H83: 38 | I83: 59.81 | J83: 1.574 | K83: 0.128 | L83: 0.925 | M83: 0.98412698 | N83: 0/1 | O83: 0.93333333 | P83: 1 | Q83: 10 | R83: 1 | T83: 2 | U83: 16 | V83: 3.6666667
A84: Jacey Clifton | B84: Advanced | C84: Ela Cross | D84: 45201 | E84: 12 | F84: 10.5 | G84: 0.875 | H84: 16 | I84: 12.88 | J84: 0.8047 | K84: 0.0918 | L84: 0.95 | M84: 1 | N84: 0/0 | O84: 0.66666667 | R84: 5 | T84: 3 | U84: 20 | V84: 3.6666667
A85: Jackson Byars | B85: Distinguished | C85: Ian Plamondon | D85: 45176 | E85: 30 | F85: 23.56 | G85: 0.7853 | H85: 38 | I85: 51.44 | J85: 1.3536 | K85: 0.2261 | L85: 0.86666667 | M85: 1 | N85: 0/3 | O85: 0.88 | R85: 4 | T85: 10 | U85: 33 | V85: 1
A86: Jacob Karn | B86: Advanced | C86: Ian Plamondon | D86: 45719 | E86: 35 | F86: 31.25 | G86: 0.8929 | H86: 43 | I86: 45.88 | J86: 1.0669 | K86: 0.2219 | L86: 0.98780488 | M86: 0.99166667 | N86: 6/11 | O86: 0.2 | R86: 10 | T86: 22 | U86: 43
A87: Jake Corvino | B87: Advanced | C87: Ela Cross | D87: 45212 | E87: 12 | F87: 7 | G87: 0.5833 | H87: 16 | I87: 17.06 | J87: 1.0664 | K87: 0.2578 | L87: 1 | M87: 0.96 | N87: 0/0 | O87: 0.18181818 | R87: 3 | T87: 0 | U87: 7
A88: Jamaul Pemberton | B88: Premium | C88: Ian Plamondon | D88: 44036 | E88: 35 | F88: 10 | G88: 0.2857 | H88: 43 | I88: 46.56 | J88: 1.0828 | K88: 0.0854 | L88: 0.91666667 | M88: 1 | N88: 0/0 | O88: 0.92307692 | T88: 1 | U88: 10
A89: James Falconer | B89: Advanced | C89: Ian Plamondon | D89: 45513 | E89: 35 | F89: 24.75 | G89: 0.7071 | H89: 43 | I89: 34.94 | J89: 0.8125 | K89: 0.1794 | L89: 0.97222222 | M89: 0.99047619 | N89: 1/2 | O89: 0.87878788 | R89: 10 | T89: 7 | U89: 41 | V89: 3.0909091
A90: Jason Keller | B90: Premium | C90: Jessica Milner | D90: 39923 | E90: 30 | F90: 15.38 | G90: 0.5125 | H90: 38 | I90: 45.25 | J90: 1.1908 | K90: 0.0884 | L90: 0.97058824 | M90: 0.96428571 | N90: 0/1 | O90: 0.58823529 | T90: 3 | U90: 16 | V90: 4.25
A91: Jason Noble | B91: Advanced | C91: Kristin Haase-Alvey | D91: 45510 | E91: 30 | F91: 22.13 | G91: 0.7375 | H91: 38 | I91: 32.13 | J91: 0.8454 | K91: 0.1912 | L91: 0.84210526 | M91: 0.95145631 | N91: 0/0 | O91: 1 | R91: 16 | T91: 4 | U91: 32 | V91: 3.7142857
A92: Jayna Boaz | B92: Advanced | C92: Ela Cross | D92: 45881 | E92: 12 | F92: 12 | G92: 1 | H92: 16 | I92: 21.38 | J92: 1.3359 | K92: 0.3507 | L92: 0.9 | M92: 0.89795918 | N92: 1/5 | O92: 0.44444444 | R92: 5 | S92: 11 | T92: 7 | U92: 16 | V92: 2
A93: Jennifer Hernandez | B93: Distinguished | C93: Kristin Haase-Alvey | D93: 45267 | E93: 20 | F93: 10.94 | G93: 0.5469 | H93: 24 | I93: 20.69 | J93: 0.862 | K93: 0.1714 | L93: 1 | M93: 1 | N93: 1/1 | O93: 0.93333333 | R93: 4 | T93: 1 | U93: 15 | V93: 3.875
A94: Jesse Squires | B94: Advanced | C94: Kristin Haase-Alvey | D94: 45702 | E94: 30 | F94: 19.13 | G94: 0.6375 | H94: 38 | I94: 34 | J94: 0.8947 | K94: 0.1111 | L94: 1 | M94: 1 | N94: 6/7 | O94: 0.95238095 | R94: 4 | S94: 3 | T94: 10 | U94: 34 | V94: 3.6923077
A95: Jessica Menkhus | B95: Premium | C95: Ela Cross | D95: 43917 | E95: 12 | F95: 6.25 | G95: 0.5208 | H95: 16 | I95: 18.81 | J95: 1.1758 | K95: 0.3023 | L95: 1 | M95: 1 | N95: 0/0 | O95: 1 | R95: 2 | T95: 0 | U95: 9 | V95: 2
A96: Jessica Peterson | B96: Premium | C96: Annelies de Groot | D96: 43812 | E96: 12 | F96: 9.38 | G96: 0.7813 | H96: 16 | I96: 24.13 | J96: 1.5078 | K96: 0.2568 | L96: 1 | M96: 0.96969697 | N96: 2/2 | O96: 0.8 | T96: 3 | U96: 8 | V96: 3
A97: Jessica Wall | B97: Advanced | C97: Kristin Haase-Alvey | D97: 45307 | E97: 30 | F97: 20.88 | G97: 0.6958 | H97: 38 | I97: 39.83 | J97: 1.0482 | K97: 0.2335 | L97: 0.98181818 | M97: 1 | N97: 2/3 | O97: 0.85714286 | R97: 8 | T97: 8 | U97: 30 | V97: 4.25
A98: Jill Watson | B98: Advanced | C98: Ian Plamondon | D98: 45968 | E98: 35 | F98: 30 | G98: 0.8571 | H98: 43 | I98: 47.88 | J98: 1.1134 | K98: 0.2837 | L98: 1 | M98: 1 | N98: 20/28 | O98: 0 | P98: 1 | Q98: 10 | R98: 12 | T98: 46 | U98: 52 | V98: 3.5
A99: Jimmy Works | B99: Distinguished | C99: Kristin Haase-Alvey | D99: 45217 | E99: 20 | F99: 10.88 | G99: 0.5438 | H99: 24 | I99: 25.33 | J99: 1.0556 | K99: 0.2289 | L99: 1 | M99: 1 | N99: 2/4 | O99: 1 | R99: 4 | T99: 6 | U99: 18 | V99: 2.875
A100: Jocelyne Nolasco | B100: Advanced | C100: Nikki Pencak | D100: 46006 | E100: 35 | F100: 0 | G100: 0 | H100: 43 | I100: 3.63 | J100: 0.0843 | N100: 0/0 | T100: 0 | U100: 0
...

Sheet MasterTutor
A1: Full Name | B1: Faculty Leader | C1: Professional/Adjunct | D1: Tier
A2: Akeema Williams | B2: Ian Plamondon | C2: Professional | D2: Advanced
A3: Alex Small | B3: Ela Cross | C3: Adjunct | D3: Premium
A4: Alexa Pinera | B4: Ian Plamondon | C4: Professional | D4: Premium
A5: Alexandra Berrios | B5: Kristin Haase-Alvey | C5: Adjunct | D5: Advanced
A6: Alexis Boucher | B6: Ian Plamondon | C6: Professional | D6: Distinguished
A7: Alison Trumbull | B7: Geoff St. Marie | C7: Adjunct | D7: Premium
A8: Allison Peck | B8: Kristin Haase-Alvey | C8: Adjunct | D8: Distinguished
A9: Amber Maldonado | B9: Annelies de Groot | C9: Professional | D9: Advanced
A10: Amelia Sain | B10: Jessica Milner | C10: Professional | D10: Premium
A11: Ana Heiser | B11: Kristin Haase-Alvey | C11: Professional | D11: Distinguished
A12: Andres Jarquin | B12: Ian Plamondon | C12: Professional | D12: Advanced
... A196: Zoe Shanley | B196: Ian Plamondon | C196: Professional | D196: Advanced

Sheet AnnualReview
A1: id | B1: tutor_name | C1: tier | D1: fl | E1: hire_date | F1: delivery_target | G1: sessions_on_time | H1: prep_time | I1: weighted_repurchase | J1: number_of_nps | K1: average_nps | L1: current_sci | M1: availability_percent

Sheet SubjectAddition
A1: emp_id | B1: tutor_name | C1: category | D1: subject | E1: created | F1: subject_sci
